{
	"format_version": "1.8.0",
	"animations": {
		"static_idle": {
			"loop": true,
			"bones": {
				"lefthand": {
					"rotation": [111.54907, -25.87501, 174.37624],
					"position": [6.425, -13.1, -12.525],
					"scale": [1, 1.5, 1]
				},
				"righthand": {
					"rotation": [92.5, -355, -180],
					"position": [-6.25, -13.275, -1.7],
					"scale": [1, 1.5, 1]
				},
				"root": {
					"rotation": [0, 0, 0],
					"position": [0, 0, 0]
				},
				"constraint": {
					"rotation": [0.2, 0.2, 0.2]
				}
			}
		},
		"draw": {
			"animation_length": 0.6667,
			"bones": {
				"root": {
					"rotation": {
						"0.0": [0, -27.5, 40],
						"0.0833": [-1.61, -25.29, 36.2],
						"0.1667": [-1.51, -16.17, 26.22],
						"0.2917": [0.2, -0.1, 7],
						"0.4167": [0, 0, -0.13],
						"0.5": [-0.00496, 0.00233, 1.13648],
						"0.6667": [0, 0, 0]
					},
					"position": {
						"0.0": [0, -6.5, 5.5],
						"0.0417": [0, -3.95, 3.68],
						"0.1667": [-0.43508, -1.32003, 0.88469],
						"0.25": [0, -0.165, 0.31],
						"0.375": [0, -0.04, 0.28],
						"0.4583": [0, -0.17, 0.22],
						"0.625": [0, 0, 0]
					}
				},
				"constraint": {
					"rotation": [0.2, 0.15, 0.2],
					"position": [0.2, 0.2, 0.4]
				},
				"lefthand": {
					"rotation": [111.54907, -25.87501, 174.37624],
					"position": [6.425, -13.1, -12.525],
					"scale": [1, 1.5, 1]
				},
				"righthand": {
					"rotation": [92.5, -355, -180],
					"position": [-6.25, -13.275, -1.7],
					"scale": [1, 1.5, 1]
				}
			}
		},
		"put_away": {
			"animation_length": 0.4333,
			"bones": {
				"root": {
					"rotation": {
						"0.0": {
							"post": [0, 0, 0],
							"lerp_mode": "catmullrom"
						},
						"0.1": {
							"post": [7.5, -15, 0],
							"lerp_mode": "catmullrom"
						},
						"0.2667": {
							"post": [3.34915, -53.64686, 15.2689],
							"lerp_mode": "catmullrom"
						},
						"0.4333": {
							"post": [-20.85115, -72.47954, 42.16438],
							"lerp_mode": "catmullrom"
						}
					},
					"position": {
						"0.0": {
							"post": [0, 0, 0],
							"lerp_mode": "catmullrom"
						},
						"0.1333": {
							"post": [1.9375, -2.84375, 0],
							"lerp_mode": "catmullrom"
						},
						"0.2": {
							"post": [1.9375, -5.84375, 0],
							"lerp_mode": "catmullrom"
						},
						"0.3333": {
							"post": [3.44, -18.7875, 0],
							"lerp_mode": "catmullrom"
						}
					}
				},
				"lefthand": {
					"rotation": [111.54907, -25.87501, 174.37624],
					"position": [6.425, -13.1, -12.525],
					"scale": [1, 1.5, 1]
				},
				"righthand": {
					"rotation": [92.5, -355, -180],
					"position": [-6.25, -13.275, -1.7],
					"scale": [1, 1.5, 1]
				},
				"camera": {
					"rotation": {
						"0.0": [0, 0, 0],
						"0.0333": [0.05, 0, -0.02],
						"0.0667": [0.12, 0, -0.04],
						"0.1": [0.18, 0, -0.07],
						"0.1333": [0.18, 0, -0.1],
						"0.1667": [0.07, 0, -0.14],
						"0.2": [-0.1, 0, -0.2],
						"0.2333": [-0.26, 0, -0.24],
						"0.2667": [-0.35, 0, -0.25],
						"0.3": [-0.32, 0, -0.21],
						"0.3333": [-0.21, 0, -0.13],
						"0.3667": [-0.08, 0, -0.05],
						"0.4": [0, 0, 0]
					}
				}
			},
			"sound_effects": {
				"0.0": {
					"effect": "wfoly_plr_sm_uzulu_drop_quick_down"
				}
			}
		},
		"shoot": {
			"animation_length": 0.6333,
			"bones": {
				"root": {
					"rotation": {
						"0.0": [0, 0, 0],
						"0.0333": [-0.32, 0, 0.49],
						"0.0667": [-2.4, 0, -1.21],
						"0.1": [-2.11, 0, 0.33],
						"0.1333": [-1.05, -0.01, 0.08],
						"0.1667": [-0.02, 0, -0.29],
						"0.2": [0.15, 0.08, -0.17],
						"0.2333": [0.1, 0.19, 0.08],
						"0.2667": [0.04, 0.24, 0.23],
						"0.3": [0.03, 0.18, 0.18],
						"0.3333": [0, 0.07, 0.05],
						"0.3667": [-0.02, -0.04, -0.09],
						"0.4": [-0.04, -0.11, -0.17],
						"0.4333": [-0.04, -0.12, -0.17],
						"0.4667": [-0.03, -0.1, -0.14],
						"0.5": [-0.02, -0.06, -0.09],
						"0.5333": [-0.01, -0.02, -0.03],
						"0.5667": [0, 0, 0]
					},
					"position": {
						"0.0": [0, 0, 0],
						"0.0333": [0, -0.06, 1.48],
						"0.0667": [0, -0.06, 1.19],
						"0.1": [0, -0.03, 0.52],
						"0.1333": [0, 0, -0.09],
						"0.1667": [0, 0, -0.15],
						"0.2": [0, 0, -0.1],
						"0.2333": [0, 0, 0],
						"0.2667": [0, 0, 0.05],
						"0.3": [0, 0, 0.05],
						"0.3333": [0, 0, 0.04],
						"0.3667": [0, 0, 0.03],
						"0.4": [0, 0, 0.01],
						"0.4333": [0, 0, 0],
						"0.4667": [0, 0, 0],
						"0.5": [0, 0, 0],
						"0.5333": [0, 0, 0],
						"0.5667": [0, 0, 0],
						"0.6": [0, 0, 0],
						"0.6333": [0, 0, 0]
					}
				},
				"bolt": {
					"position": {
						"0.0": [0, 0, 0],
						"0.0333": [0, 0, 3],
						"0.0667": [0, 0, 0]
					}
				},
				"bullet_in_barrel": {
					"position": {
						"0.0333": [0, -0.6, 0],
						"0.0667": [0, 0, 0]
					}
				},
				"constraint": {
					"rotation": {
						"0.0": [0.2, 0.2, 0.2],
						"0.1": [0.1, 0.2, 0.4],
						"0.3": [0, 0, 0]
					},
					"position": {
						"0.1": [0.2, 0.02, 0.35],
						"0.3": [0, 0, 0]
					}
				},
				"camera": {
					"rotation": {
						"0.0": [0, 0, 0],
						"0.0333": [0, 0, 0.7],
						"0.0667": [0, 0, -0.32],
						"0.1": [0, 0, -0.06],
						"0.1333": [0, 0, 0.28],
						"0.1667": [0, 0, 0.06],
						"0.2": [0, 0, -0.2],
						"0.2333": [0, 0, -0.1],
						"0.2667": [0, 0, 0.05],
						"0.3": [0, 0, 0.04],
						"0.3333": [0, 0, 0]
					}
				}
			},
			"sound_effects": {
				"0.0": {
					"effect": "weap_mpapa5_fire_first_plr_01"
				}
			}
		},
		"reload_tactical": {
			"loop": "hold_on_last_frame",
			"animation_length": 2,
			"bones": {
				"lefthand": {
					"rotation": [111.54907, -25.87501, 174.37624],
					"position": {
						"0.0": [6.425, -13.1, -12.525],
						"0.0667": [6.42, -13.1, -12.52],
						"0.1333": [8.42, -13.1, -10.52],
						"0.2": [7.42, -13.1, -7.52],
						"0.2333": [7.42, -13.1, -7.52],
						"0.3": [7.42, -14.1, -7.52],
						"0.4667": [7.42, -14.1, -7.52],
						"0.8": [7.42, -17.1, -7.52],
						"1.1": [7.42, -17.1, -7.52],
						"1.1333": [7.42, -17.1, -7.52],
						"1.2": [7.42, -17.1, -7.52],
						"1.4": [9.545, -15.075, -7.52],
						"1.5333": [8.42, -13.1, -10.52],
						"1.7": [6.425, -13.1, -12.525]
					},
					"scale": [1, 1.5, 1]
				},
				"righthand": {
					"rotation": [92.5, -355, -180],
					"position": [-6.25, -13.275, -1.7],
					"scale": [1, 1.5, 1]
				},
				"root": {
					"rotation": {
						"0.0": [0, 0, 0.01],
						"0.0333": [-10.51, -2.6, -2.39],
						"0.0667": [-19.33, -4.68, -3.43],
						"0.1": [-27.72, -8.17, -6.67],
						"0.1333": [-32.52, -11.87, -10.56],
						"0.1667": [-36.49, -14.7, -14],
						"0.2": [-37.64, -18, -17.62],
						"0.2333": [-38.79, -19.6, -18.73],
						"0.2667": [-39.94, -21.6, -19.85],
						"0.3": [-42.09, -24.9, -22.07],
						"0.3333": [-42.9, -26.07, -26.36],
						"0.3667": [-43.09, -25.96, -29.54],
						"0.4": [-43.84, -24.78, -27.38],
						"0.4333": [-43.56, -24.19, -25.96],
						"0.4667": [-42.86, -24.1, -25.87],
						"0.5": [-41.97, -24.11, -25.96],
						"0.5333": [-41.11, -24.27, -26.14],
						"0.5667": [-40.53, -24.62, -26.3],
						"0.6": [-40.25, -25.83, -26.66],
						"0.6333": [-40.32, -27.44, -27.09],
						"0.6667": [-40.38, -28.46, -27.24],
						"0.7": [-40.37, -28.36, -26.61],
						"0.7333": [-40.09, -27.11, -25.6],
						"0.7667": [-39.91, -26.95, -26.76],
						"0.8": [-39.72, -26.79, -27.91],
						"0.8333": [-39.54, -26.64, -29.07],
						"0.8667": [-39.36, -26.48, -30.22],
						"0.9": [-39.17, -26.33, -31.38],
						"0.9333": [-38.99, -26.18, -32.54],
						"0.9667": [-38.81, -26.02, -33.7],
						"1.0": [-36.79, -25.79, -33.83],
						"1.0333": [-35.18, -25.43, -33.03],
						"1.0667": [-34.7, -24.67, -32.71],
						"1.1": [-35.3, -25.3, -32.56],
						"1.1333": [-40.38, -25.29, -33.33],
						"1.1667": [-37.4, -27.34, -30.31],
						"1.2": [-39.08, -30.41, -29.93],
						"1.2333": [-34.19, -32.26, -30.8],
						"1.2667": [-33.05, -29.79, -32.6],
						"1.3": [-36.78, -26.6, -28.08],
						"1.3333": [-35.95, -26.58, -28.91],
						"1.3667": [-34.22, -26.96, -29.9],
						"1.4": [-32.58, -27.36, -28.65],
						"1.4333": [-30.8, -26.96, -26.65],
						"1.4667": [-30.34, -25.98, -25.98],
						"1.5": [-29.85, -24.33, -25.2],
						"1.5333": [-27.19, -20.98, -22.45],
						"1.5667": [-23.51, -17.34, -18.81],
						"1.6": [-18.45, -12.49, -13.82],
						"1.6333": [-12.91, -7.33, -8.43],
						"1.6667": [-7.79, -2.74, -3.65],
						"1.7": [-4, 0.39, -0.46],
						"1.7333": [-1.31, 1.81, 0.88],
						"1.7667": [0.07, 1.53, 0.43],
						"1.8": [0.67, 0.58, 1.95],
						"1.8333": [0.53, 0.39, 1.47],
						"1.8667": [0.39, 0.19, 0.98],
						"1.9": [0.25, 0, 0.5],
						"1.9333": [0.25, 0, 0.5],
						"1.9667": [0.25, 0, 0.5]
					},
					"position": {
						"0.0": [0, 0, 0],
						"0.0333": [-0.25, -0.35, -0.34],
						"0.0667": [-0.56, -0.6, -0.61],
						"0.1": [-0.83, -0.54, -0.66],
						"0.1333": [-1.05, -0.76, -0.44],
						"0.1667": [-1.26, -1.01, -0.19],
						"0.2": [-1.29, -1.2, 0.11],
						"0.2333": [-1.32, -1.39, 0.4],
						"0.2667": [-1.35, -1.58, 0.5],
						"0.3": [-1.36, -1.55, 0.44],
						"0.3333": [-1.35, -1.39, 0.18],
						"0.3667": [-1.35, -1.28, -0.03],
						"0.4": [-1.35, -1.25, -0.24],
						"0.4333": [-1.35, -1.27, -0.21],
						"0.4667": [-1.35, -1.33, -0.16],
						"0.5": [-1.35, -1.36, -0.2],
						"0.5333": [-1.35, -1.37, -0.31],
						"0.5667": [-1.35, -1.35, -0.45],
						"0.6": [-1.36, -1.29, -0.53],
						"0.6333": [-1.37, -1.2, -0.61],
						"0.6667": [-1.38, -1.11, -0.7],
						"0.7": [-1.38, -1.04, -0.79],
						"0.7333": [-1.35, -1.03, -0.87],
						"0.7667": [-1.33, -1.05, -0.87],
						"0.8": [-1.32, -1.07, -0.87],
						"0.8333": [-1.3, -1.09, -0.87],
						"0.8667": [-1.29, -1.11, -0.87],
						"0.9": [-1.27, -1.12, -0.87],
						"0.9333": [-1.26, -1.14, -0.88],
						"0.9667": [-1.24, -1.16, -0.88],
						"1.0": [-1.26, -1.19, -0.85],
						"1.0333": [-1.23, -1.31, -0.87],
						"1.0667": [-1.21, -1.47, -0.89],
						"1.1": [-1.24, -1.58, -0.88],
						"1.1333": [-1.19, -1.4, -0.68],
						"1.1667": [-1.16, -1.34, -0.75],
						"1.2": [-1.07, -1.33, -0.88],
						"1.2333": [-1.03, -1.37, -0.97],
						"1.2667": [-0.99, -1.44, -1.07],
						"1.3": [-0.93, -1.52, -1.15],
						"1.3333": [-0.87, -1.61, -1.2],
						"1.3667": [-0.81, -1.74, -1.25],
						"1.4": [-0.74, -1.83, -1.25],
						"1.4333": [-0.64, -1.84, -1.16],
						"1.4667": [-0.56, -1.78, -1.03],
						"1.5": [-0.47, -1.68, -0.85],
						"1.5333": [-0.37, -1.55, -0.63],
						"1.5667": [-0.26, -1.4, -0.39],
						"1.6": [-0.17, -1.27, -0.18],
						"1.6333": [-0.09, -1.16, 0.01],
						"1.6667": [-0.03, -1.1, 0.13],
						"1.7": [-0.01, -1.12, 0.18],
						"1.7333": [-0.06, -1.25, 0.09],
						"1.7667": [-0.11, -0.95, 0],
						"1.8": [-0.12, -0.57, -0.02],
						"1.8333": [-0.06, -0.29, -0.01],
						"1.8667": [0, 0, 0],
						"1.9": [0, 0, 0],
						"1.9333": [0, 0, 0],
						"1.9667": [0, 0, 0]
					}
				},
				"mag_and_lefthand": {
					"rotation": {
						"0.0": [0, 0, 0],
						"0.2667": [0, 0, 0],
						"1.5333": [0, 0, 0]
					},
					"position": {
						"0.0": [0, 0, 0],
						"0.2667": [0, 0, 0],
						"0.3333": [0, -3, 0],
						"0.3667": [0, -82, 0],
						"0.9": [0, -82, 0],
						"1.0333": [0, -32.43, 0],
						"1.0667": [0, -9.62, 0],
						"1.1333": [0, 0, 0],
						"1.5333": [0, 0, 0]
					}
				},
				"camera": {
					"rotation": {
						"0.0": [0, 0, 0],
						"0.0333": [0.01, 0.03, 0.08],
						"0.0667": [0.03, 0.06, 0.19],
						"0.1": [0.04, 0.1, 0.28],
						"0.1333": [0.05, 0.13, 0.3],
						"0.1667": [0.04, 0.14, 0.14],
						"0.2": [0.02, 0.14, -0.12],
						"0.2333": [0, 0.1, -0.32],
						"0.2667": [-0.02, -0.02, -0.42],
						"0.3": [-0.04, -0.18, -0.46],
						"0.3333": [-0.05, -0.25, -0.47],
						"0.3667": [-0.05, -0.14, -0.46],
						"0.4": [-0.04, 0.05, -0.41],
						"0.4333": [0, 0.18, -0.34],
						"0.4667": [0.09, 0.15, -0.24],
						"0.5": [0.2, 0.05, -0.12],
						"0.5333": [0.25, 0, -0.02],
						"0.5667": [0.19, 0.08, 0.03],
						"0.6": [0.08, 0.21, 0.06],
						"0.6333": [0, 0.25, 0.08],
						"0.6667": [-0.02, -0.04, 0.17],
						"0.7": [0, -0.32, 0.2],
						"0.7333": [0, -0.27, 0.08],
						"0.7667": [0, -0.12, -0.11],
						"0.9": [0, 0, -0.2],
						"0.9333": [0, 0.02, -0.11],
						"0.9667": [0.01, 0.01, 0.07],
						"1.0": [0, 0, 0.2],
						"1.0333": [-0.09, 0.05, 0.23],
						"1.0667": [-0.12, 0, 0.1],
						"1.1": [0.13, -0.43, -0.38],
						"1.1333": [0.35, -0.73, -0.7],
						"1.1667": [0.2, -0.24, -0.12],
						"1.2": [0, 0.3, 0.53],
						"1.2333": [-0.02, 0.29, 0.54],
						"1.2667": [0, 0.14, 0.38],
						"1.3": [0, 0, 0.23],
						"1.3333": [-0.04, -0.08, 0.12],
						"1.3667": [-0.1, -0.15, 0.02],
						"1.4": [-0.12, -0.17, -0.07],
						"1.4333": [-0.11, -0.15, -0.15],
						"1.4667": [-0.07, -0.1, -0.23],
						"1.5": [-0.03, -0.05, -0.29],
						"1.5333": [0, 0, -0.32],
						"1.5667": [0.02, 0.03, -0.3],
						"1.6": [0.03, 0.06, -0.25],
						"1.6333": [0.04, 0.08, -0.18],
						"1.6667": [0.05, 0.09, -0.12],
						"1.7": [0.05, 0.1, -0.07],
						"1.7333": [0.04, 0.09, -0.04],
						"1.7667": [0.03, 0.06, -0.02],
						"1.8": [0.01, 0.02, -0.01],
						"1.8333": [0, 0, 0],
						"1.8667": [0, 0, 0.02],
						"1.9": [0, 0, 0.03],
						"1.9333": [0, 0, 0.05],
						"1.9667": [0, 0, 0.02],
						"2.0": [0, 0, 0]
					}
				},
				"constraint": {
					"rotation": [0.2, 0.2, 0.2]
				},
				"mag_and_bullet": {
					"rotation": {
						"0.0": [0, 0, 0],
						"0.3": [0, 0, 0],
						"0.3333": [0, 0, 0]
					},
					"position": {
						"0.0": [0, 0, 0],
						"0.3": [0, 0, 0],
						"0.3333": [0, 0, 0]
					}
				}
			},
			"sound_effects": {
				"0.0": {
					"effect": "ex:mp5/mp5_sleight_of_hand_tactical"
				}
			}
		},
		"reload_empty": {
			"loop": "hold_on_last_frame",
			"animation_length": 2.4,
			"bones": {
				"lefthand": {
					"rotation": [111.54907, -25.87501, 174.37624],
					"position": {
						"0.0": [6.425, -13.1, -12.525],
						"0.0667": [7.42, -13.1, -12.52],
						"0.1333": [10.25, -13.1, -12.52],
						"0.2": [9.48, -8.1, -13.52],
						"0.2667": [9.48, -7.1, -14.52],
						"0.3": [9.48, -7.1, -11.52],
						"0.3333": [8.58, -6.45, -11.145],
						"0.5667": [6.42, -12.1, -7.52],
						"0.6333": [9.42, -15.1, -8.52],
						"0.7": [7.42, -13.1, -7.52],
						"0.7333": [7.42, -13.1, -7.52],
						"0.8": [7.42, -14.1, -7.52],
						"0.9667": [7.42, -14.1, -7.52],
						"1.5": [7.42, -17.1, -7.52],
						"1.6": [8.42, -7.1, -11.52],
						"1.6667": [8.92, -7.6, -11.02],
						"1.8": [9.42, -9.1, -11.52],
						"1.8333": [8.42, -10.1, -11.52],
						"1.8667": [8.42, -13.1, -11.52],
						"1.9667": [6.425, -13.1, -12.525]
					},
					"scale": [1, 1.5, 1]
				},
				"righthand": {
					"rotation": [92.5, -355, -180],
					"position": [-6.25, -13.275, -1.7],
					"scale": [1, 1.5, 1]
				},
				"root": {
					"rotation": {
						"0.0": [0, 0, 0.01],
						"0.0333": [-10.51, -3, 0.36],
						"0.0667": [-19.33, -4.68, -0.28],
						"0.1": [-27.72, -8.17, -2.72],
						"0.1333": [-32.52, -12.27, -7.81],
						"0.1667": [-36.49, -16.4, -11.55],
						"0.2": [-37.64, -18, -13.4],
						"0.2333": [-38.79, -19.6, -15.25],
						"0.2667": [-39.94, -21.2, -17.1],
						"0.3": [-42.09, -24.9, -19.32],
						"0.3333": [-42.9, -26.07, -23.61],
						"0.3667": [-43.09, -25.96, -26.79],
						"0.4": [-43.84, -24.78, -24.63],
						"0.4333": [-43.56, -24.19, -23.21],
						"0.4667": [-42.86, -24.1, -23.12],
						"0.5": [-41.97, -24.11, -23.21],
						"0.5333": [-41.11, -24.27, -23.39],
						"0.5667": [-40.53, -24.62, -23.55],
						"0.6": [-40.25, -25.83, -23.91],
						"0.6333": [-40.32, -27.44, -24.34],
						"0.6667": [-40.38, -28.46, -24.49],
						"0.7": [-40.37, -28.36, -23.86],
						"0.7333": [-40.09, -27.11, -22.85],
						"0.7667": [-39.99, -27.03, -23.43],
						"0.8": [-39.9, -26.96, -24],
						"0.8333": [-39.81, -26.88, -24.58],
						"0.8667": [-39.72, -26.8, -25.16],
						"0.9": [-39.62, -26.72, -25.74],
						"0.9333": [-39.53, -26.64, -26.32],
						"0.9667": [-39.44, -26.56, -26.89],
						"1.0": [-39.35, -26.49, -27.47],
						"1.0333": [-39.26, -26.41, -28.05],
						"1.0667": [-39.17, -26.34, -28.63],
						"1.1": [-39.08, -26.26, -29.21],
						"1.1333": [-38.99, -26.18, -29.79],
						"1.1667": [-38.9, -26.1, -30.37],
						"1.2": [-38.81, -26.02, -30.95],
						"1.2333": [-36.79, -25.79, -31.08],
						"1.2667": [-35.18, -25.43, -30.28],
						"1.3": [-34.7, -24.67, -29.96],
						"1.3333": [-35.3, -25.3, -29.81],
						"1.3667": [-40.38, -29.69, -30.58],
						"1.4": [-37.4, -27.34, -27.56],
						"1.4333": [-39.08, -30.41, -27.18],
						"1.4667": [-34.19, -32.26, -28.05],
						"1.5": [-33.05, -29.79, -29.85],
						"1.5333": [-36.78, -26.6, -25.33],
						"1.5667": [-35.95, -26.58, -26.16],
						"1.6": [-34.22, -26.96, -27.15],
						"1.6333": [-32.58, -27.36, -25.9],
						"1.6667": [-30.8, -26.96, -23.9],
						"1.7": [-30.34, -25.98, -23.23],
						"1.7333": [-29.85, -24.33, -22.45],
						"1.7667": [-27.19, -20.98, -19.7],
						"1.8": [-23.51, -17.34, -16.06],
						"1.8333": [-18.45, -12.49, -11.07],
						"1.8667": [-12.91, -7.33, -5.68],
						"1.9": [-7.79, -2.74, -0.9],
						"1.9333": [-4, 0.39, 2.29],
						"1.9667": [-1.31, 1.81, 3.63],
						"2.0": [0.07, 1.53, 3.18],
						"2.0333": [0.67, 0.58, 1.95],
						"2.0667": [1, 0, 1],
						"2.1": [0.23, -0.03, -0.46],
						"2.1333": [-1, -0.01, -1.5],
						"2.1667": [-0.69, -0.01, -1],
						"2.2": [-0.37, -0.01, -0.5],
						"2.2333": [-0.06, 0, 0],
						"2.2667": [0.25, 0, 0.5],
						"2.3": [0.17, 0, 0.33],
						"2.3333": [0.08, 0, 0.17],
						"2.3667": [0, 0, 0.01],
						"2.4": [0, 0, 0.01]
					},
					"position": {
						"0.0": [0, 0, 0],
						"0.0333": [-0.25, -0.2, -0.34],
						"0.0667": [-0.56, -0.35, -0.51],
						"0.1": [-0.73, -0.29, -0.535],
						"0.1333": [-0.75, -0.51, -0.34],
						"0.1667": [-0.76, -0.76, -0.19],
						"0.2": [-0.79, -0.95, 0.11],
						"0.2333": [-0.82, -1.14, 0.4],
						"0.2667": [-0.85, -1.33, 0.7],
						"0.3": [-0.86, -1.3, 0.54],
						"0.3333": [-0.85, -1.14, 0.08],
						"0.3667": [-0.85, -1.03, -0.23],
						"0.4": [-0.85, -1, -0.24],
						"0.4333": [-0.85, -1.02, -0.21],
						"0.4667": [-0.85, -1.08, -0.16],
						"0.5": [-0.85, -1.11, -0.2],
						"0.5333": [-0.85, -1.12, -0.31],
						"0.5667": [-0.85, -1.1, -0.45],
						"0.6": [-0.86, -1.04, -0.53],
						"0.6333": [-0.87, -0.95, -0.61],
						"0.6667": [-0.88, -0.86, -0.7],
						"0.7": [-0.88, -0.79, -0.79],
						"0.7333": [-0.85, -0.78, -0.87],
						"0.7667": [-0.84, -0.79, -0.87],
						"0.8": [-0.83, -0.8, -0.87],
						"0.8333": [-0.82, -0.81, -0.87],
						"0.8667": [-0.81, -0.82, -0.87],
						"0.9": [-0.8, -0.83, -0.87],
						"0.9333": [-0.79, -0.84, -0.87],
						"0.9667": [-0.79, -0.85, -0.87],
						"1.0": [-0.78, -0.86, -0.87],
						"1.0333": [-0.77, -0.87, -0.87],
						"1.0667": [-0.76, -0.88, -0.87],
						"1.1": [-0.75, -0.89, -0.87],
						"1.1333": [-0.75, -0.9, -0.87],
						"1.1667": [-0.74, -0.9, -0.87],
						"1.2": [-0.74, -0.91, -0.88],
						"1.2333": [-0.76, -0.94, -0.85],
						"1.2667": [-0.73, -1.06, -0.87],
						"1.3": [-0.71, -1.22, -0.89],
						"1.3333": [-0.74, -1.33, -0.88],
						"1.3667": [-1.19, -1.15, -0.68],
						"1.4": [-1.16, -1.09, -0.75],
						"1.4333": [-1.07, -1.08, -0.88],
						"1.4667": [-1.03, -1.12, -0.97],
						"1.5": [-0.99, -1.19, -1.07],
						"1.5333": [-0.93, -1.27, -1.15],
						"1.5667": [-0.87, -1.36, -1.2],
						"1.6": [-0.81, -1.49, -1.25],
						"1.6333": [-0.74, -1.58, -1.25],
						"1.6667": [-0.64, -1.59, -1.16],
						"1.7": [-0.56, -1.53, -1.03],
						"1.7333": [-0.47, -1.43, -0.85],
						"1.7667": [-0.37, -1.3, -0.63],
						"1.8": [-0.26, -1.15, -0.39],
						"1.8333": [-0.17, -1.02, -0.18],
						"1.8667": [-0.09, -0.91, 0.01],
						"1.9": [-0.03, -0.85, 0.13],
						"1.9333": [-0.01, -0.87, 0.18],
						"1.9667": [-0.06, -1, 0.09],
						"2.0": [-0.11, -1.1, 0],
						"2.0333": [-0.12, -1.12, -0.02],
						"2.0667": [-0.12, -1.12, -0.02],
						"2.1": [-0.11, -1.1, 0],
						"2.1333": [-0.05, -0.95, 0.13],
						"2.1667": [0.01, -0.7, 0.22],
						"2.2": [0, -0.3, 0.11],
						"2.2333": [0, 0, 0],
						"2.2667": [0, 0, 0],
						"2.3": [0, 0, 0],
						"2.3333": [0, 0, 0],
						"2.3667": [0, 0, 0],
						"2.4": [0, 0, 0]
					}
				},
				"mag_and_lefthand": {
					"rotation": {
						"0.0": [0, 0, 0],
						"0.2333": [0, 0, 0],
						"0.5667": [0, 0, 0],
						"1.7333": [0, 0, 0]
					},
					"position": {
						"0.0": [0, 0, 0],
						"0.2333": [0, 0, 0],
						"0.5667": [0, 0, 0],
						"0.6333": [0, -3, 0],
						"0.6667": [0, -82, 0],
						"1.1": [0, -82, 0],
						"1.2333": [0, -32.43, 0],
						"1.2667": [0, -9.62, 0],
						"1.3333": [0, 0, 0],
						"1.7333": [0, 0, 0]
					}
				},
				"constraint": {
					"rotation": [0.2, 0.2, 0.2]
				},
				"mag_and_bullet": {
					"rotation": {
						"0.0": [0, 0, 0],
						"0.5667": [0, 0, 0],
						"0.6": [0, 0, 0]
					},
					"position": {
						"0.0": [0, 0, 0],
						"0.5667": [0, 0, 0],
						"0.6": [0, 0, 0]
					}
				},
				"charge_handle": {
					"rotation": {
						"0.0": [0, 0, 0],
						"0.3": [0, 0, 0],
						"0.3333": [0, 0, -40],
						"1.6": [0, 0, -40],
						"1.6333": [0, 0, -40],
						"1.7": [0, 0, 0]
					},
					"position": {
						"0.0": [0, 0, 0],
						"0.2667": [0, 0, 0],
						"0.3": [0, 0, 3],
						"1.6333": [0, 0, 3],
						"1.6667": [0, 0, 3],
						"1.7": [0, 0, 0]
					}
				},
				"camera": {
					"rotation": {
						"0.0": [0, 0, 0],
						"0.0333": [0.01, 0.03, 0.08],
						"0.0667": [0.03, 0.06, 0.19],
						"0.1": [0.04, 0.1, 0.28],
						"0.1333": [0.05, 0.13, 0.3],
						"0.1667": [0.04, 0.14, 0.14],
						"0.2": [0.02, 0.14, -0.12],
						"0.2333": [0, 0.1, -0.32],
						"0.2667": [-0.02, -0.02, -0.42],
						"0.3": [-0.04, -0.18, -0.46],
						"0.3333": [-0.05, -0.25, -0.47],
						"0.3667": [-0.05, -0.14, -0.46],
						"0.4": [-0.04, 0.05, -0.41],
						"0.4333": [0, 0.18, -0.34],
						"0.4667": [0.09, 0.15, -0.24],
						"0.5": [0.2, 0.05, -0.12],
						"0.5333": [0.25, 0, -0.02],
						"0.5667": [0.19, 0.08, 0.03],
						"0.6": [0.08, 0.21, 0.06],
						"0.6333": [0, 0.25, 0.08],
						"0.6667": [-0.02, -0.04, 0.17],
						"0.7": [0, -0.32, 0.2],
						"0.7333": [0, -0.27, 0.08],
						"0.7667": [0, -0.12, -0.11],
						"0.8": [0, 0, -0.2],
						"0.8333": [0, 0.02, -0.11],
						"0.8667": [0.01, 0.01, 0.07],
						"0.9": [0, 0, 0.2],
						"0.9333": [-0.09, 0.05, 0.23],
						"0.9667": [-0.12, 0, 0.1],
						"1.3333": [0.13, -0.43, -0.38],
						"1.3667": [0.35, -0.73, -0.7],
						"1.4": [0.2, -0.24, -0.12],
						"1.4333": [0, 0.3, 0.53],
						"1.4667": [-0.02, 0.29, 0.54],
						"1.5": [0, 0.14, 0.38],
						"1.5333": [0, 0, 0.23],
						"1.5667": [-0.04, -0.08, 0.12],
						"1.6": [-0.1, -0.15, 0.02],
						"1.6333": [-0.12, -0.17, -0.07],
						"1.6667": [-0.11, -0.15, -0.15],
						"1.7": [-0.07, -0.1, -0.23],
						"1.7333": [-0.03, -0.05, -0.29],
						"1.7667": [0, 0, -0.32],
						"1.8": [0.02, 0.03, -0.3],
						"1.8333": [0.03, 0.06, -0.25],
						"1.8667": [0.04, 0.08, -0.18],
						"1.9": [0.05, 0.09, -0.12],
						"1.9333": [0.05, 0.1, -0.07],
						"1.9667": [0.04, 0.09, -0.04],
						"2.0": [0.03, 0.06, -0.02],
						"2.0333": [0.01, 0.02, -0.01],
						"2.0667": [0, 0, 0],
						"2.1": [0, 0, 0.02],
						"2.1333": [0, 0, 0.03],
						"2.1667": [0, 0, 0.05],
						"2.2": [0, 0, 0.02],
						"2.2333": [0, 0, 0]
					}
				}
			},
			"sound_effects": {
				"0.0": {
					"effect": "ex:mp5/mp5_sleight_of_hand_empty"
				}
			}
		},
		"inspect": {
			"animation_length": 5.7917,
			"bones": {
				"root": {
					"rotation": {
						"0.0": [0, 0, 0],
						"0.0417": [-5.79, 0.13, 1.95],
						"0.1667": [-17.59, -10.78, -12.86],
						"0.25": [-25.6, -24.52, -35.41],
						"0.2917": [-27.59976, -27.22756, -41.19159],
						"0.3333": [-29.18247, -28.58725, -44.21775],
						"0.4167": [-31.13848, -27.68974, -42.19082],
						"0.5": [-30.66598, -28.14222, -43.20004],
						"0.5833": [-31.42, -28.14, -43.2],
						"0.7083": [-32.01, -27.44, -41.92],
						"0.9167": [-31.74, -28, -42.94],
						"1.0": [-31.76, -28.22, -43.36],
						"1.5": [-31.20393, -28.6466, -44.18009],
						"1.5417": [-29.85, -30.65, -48.19],
						"1.6667": [-29.18045, -31.65513, -50.18764],
						"1.7917": [-29.71221, -31.16351, -49.16731],
						"1.9583": [-29.71, -31.16, -49.17],
						"2.2083": [-29.1733, -31.63628, -50.20015],
						"2.2917": [-28.77, -30.86, -48.82],
						"2.4167": [-27.89, -26.22, -40.22],
						"2.4583": [-26.12, -16.94, -23.01],
						"2.5": [-27.22851, -1.49811, -0.30357],
						"2.6667": [-27.64133, 24.07175, 55.7761],
						"2.7917": [-27.55942, 24.18741, 56.01913],
						"2.9167": [-26.63512, 25.213, 58.2211],
						"3.0833": [-27.05095, 24.76144, 57.23672],
						"3.2917": [-27.18, 24.27, 56.94],
						"3.5": [-27.3, 24.11, 56.64],
						"3.75": [-27.43825, 24.30227, 56.26287],
						"3.9583": [-27.13612, 27.9047, 59.22256],
						"4.125": [-27.60586, 27.4605, 58.21082],
						"4.3333": [-27.25, 27.82, 58.99],
						"4.5417": [-27.1, 27.74, 59.31],
						"4.7083": [-26.95, 27.21, 59.62],
						"4.7917": [-26.5, 25.14, 57.6],
						"4.9167": [-25.69, 21.35, 53.37],
						"5.0": [-27.3, 13.08, 39.44],
						"5.1667": [-17.16969, -2.07286, 18.42359],
						"5.25": [-0.18485, -1.03643, 9.2118],
						"5.375": [1.9612, -0.55625, 7.98076],
						"5.5": [0.66898, -0.48139, 1.31942],
						"5.5833": [-1.00521, -0.46117, 2.73757],
						"5.75": [0, 0, 0]
					},
					"position": {
						"0.0": [0, 0, 0],
						"0.0833": [-0.07, 0.63, 0],
						"0.1667": [-0.13, 1, 0],
						"0.25": [-0.51, 1.07, 0],
						"0.3333": {
							"pre": [-0.6, 1.3, 0],
							"post": [-0.8, 1.3, 0],
							"lerp_mode": "catmullrom"
						},
						"0.4583": {
							"post": [-0.8, 1.5, 0],
							"lerp_mode": "catmullrom"
						},
						"0.5417": {
							"post": [-0.8, 1.5, 0],
							"lerp_mode": "catmullrom"
						},
						"0.6667": {
							"post": [-0.8, 1.5, 0],
							"lerp_mode": "catmullrom"
						},
						"0.75": {
							"post": [-0.8, 1.5, 0],
							"lerp_mode": "catmullrom"
						},
						"0.8333": {
							"post": [-0.8, 1.5, 0],
							"lerp_mode": "catmullrom"
						},
						"1.0": [-0.8, 1.5, 0],
						"1.25": [-0.8, 1.5, 0],
						"1.5": [-0.8, 1.5, 0],
						"1.5833": {
							"pre": [-0.8, 1.5, 0],
							"post": [-1, 1.5, 0],
							"lerp_mode": "catmullrom"
						},
						"1.9583": {
							"post": [-0.8, 1.5, 0],
							"lerp_mode": "catmullrom"
						},
						"2.0417": {
							"post": [-0.8, 1.5, 0],
							"lerp_mode": "catmullrom"
						},
						"2.25": [-0.8, 1.5, 0],
						"2.3333": [-0.8, 1.5, 0],
						"2.4583": [0.35, 1.5, -0.9],
						"2.5833": [0.95, 1.7, -1.2],
						"2.75": [1.6, 2.38, -1.3],
						"2.8333": [1.6, 2.38, -1.3],
						"3.0": {
							"pre": [1.6, 2.38, -1.3],
							"post": [1.6, 2.38, -1.3],
							"lerp_mode": "catmullrom"
						},
						"3.2083": {
							"post": [1.6, 2.38, -1.3],
							"lerp_mode": "catmullrom"
						},
						"3.75": [1.6, 2.38, -1.3],
						"4.0417": [1.6, 2.38, -1.3],
						"4.3333": [1.6, 2.38, -1.3],
						"4.9583": [1.6, 2.38, -1.3],
						"5.0833": [0.48, 1.055, -1.12],
						"5.2083": [0, 0.1, -0.3],
						"5.5417": [0, 0, 0.22],
						"5.625": [0, -0.2, -0.17],
						"5.7917": [0, 0, 0]
					}
				},
				"lefthand": {
					"rotation": {
						"0.0": [111.54907, -25.87501, 174.37624],
						"5.25": [111.54907, -25.87501, 174.37624]
					},
					"position": {
						"0.0": [6.425, -13.1, -12.525],
						"0.5": [10.89, -15.62, 25.26],
						"2.25": [-3.11, -29.62, 25.26],
						"2.5": [6.8937, -12.62, -7.745],
						"4.9583": [6.8937, -12.62, -7.745],
						"5.25": [6.425, -13.1, -12.525]
					},
					"scale": {
						"0.0": [1, 1.5, 1],
						"0.5": [0, 0, 0],
						"2.25": [0, 0, 0],
						"2.4583": [1, 1, 1],
						"2.5": [1, 1.5, 1],
						"4.9583": [1, 1.5, 1]
					}
				},
				"righthand": {
					"rotation": [92.5, -355, -180],
					"position": [-6.25, -13.275, -1.7],
					"scale": [1, 1.5, 1]
				},
				"camera": {
					"rotation": {
						"0.0": {
							"post": [0, 0, 0],
							"lerp_mode": "catmullrom"
						},
						"0.0833": {
							"post": [2.38, 1.14, 0],
							"lerp_mode": "catmullrom"
						},
						"0.2083": {
							"post": [2.43, 2.29, 0],
							"lerp_mode": "catmullrom"
						},
						"0.2917": {
							"post": [1.29, 2.86, 0],
							"lerp_mode": "catmullrom"
						},
						"0.4167": {
							"post": [-1, 4, 0],
							"lerp_mode": "catmullrom"
						},
						"0.5833": {
							"post": [-2.00275, 4.99939, -0.03503],
							"lerp_mode": "catmullrom"
						},
						"0.9167": {
							"post": [-1.25, 5, -0.04],
							"lerp_mode": "catmullrom"
						},
						"1.2083": {
							"post": [-1.53, 5.54, -0.05],
							"lerp_mode": "catmullrom"
						},
						"1.4167": {
							"post": [-1.9, 5.77, -0.05],
							"lerp_mode": "catmullrom"
						},
						"1.7083": {
							"post": [-2.6, 6, -0.05],
							"lerp_mode": "catmullrom"
						},
						"1.9167": {
							"post": [-2.45, 6, -0.05],
							"lerp_mode": "catmullrom"
						},
						"2.0833": {
							"post": [-2.62, 6, -0.05],
							"lerp_mode": "catmullrom"
						},
						"2.25": {
							"post": [-3, 6, -0.05],
							"lerp_mode": "catmullrom"
						},
						"2.4167": {
							"post": [-0.74, 3.75, 0.02],
							"lerp_mode": "catmullrom"
						},
						"2.5": {
							"post": [0.26, 2.75, 0.06],
							"lerp_mode": "catmullrom"
						},
						"2.5833": {
							"post": [0.76, 2.25, 0.08],
							"lerp_mode": "catmullrom"
						},
						"2.7917": {
							"post": [1.76, 1.75, 0.08],
							"lerp_mode": "catmullrom"
						},
						"2.9167": {
							"post": [1.47, 1.75, 0.08],
							"lerp_mode": "catmullrom"
						},
						"3.0": {
							"post": [1.4, 1.75, 0.08],
							"lerp_mode": "catmullrom"
						},
						"3.1667": {
							"post": [1.32, 1.75, 0.08],
							"lerp_mode": "catmullrom"
						},
						"3.3333": {
							"post": [1.06, 1.75, 0.08],
							"lerp_mode": "catmullrom"
						},
						"3.7083": {
							"post": [0.36, 1.75, 0.08],
							"lerp_mode": "catmullrom"
						},
						"3.7917": {
							"post": [0.04, 1.75, 0.08],
							"lerp_mode": "catmullrom"
						},
						"3.9167": {
							"post": [-0.41, 1.75, 0.08],
							"lerp_mode": "catmullrom"
						},
						"4.0417": {
							"post": [-0.82, 1.75, 0.08],
							"lerp_mode": "catmullrom"
						},
						"4.4167": {
							"post": [-0.77, 1.75, 0.08],
							"lerp_mode": "catmullrom"
						},
						"4.5833": {
							"post": [-0.75, 1.75, 0.08],
							"lerp_mode": "catmullrom"
						},
						"4.7917": {
							"post": [-0.74, 1.75, 0.08],
							"lerp_mode": "catmullrom"
						},
						"4.9167": {
							"post": [1.29018, 1.7103, 1.07967],
							"lerp_mode": "catmullrom"
						},
						"5.0": {
							"post": [2.13, 1.06, 0.67],
							"lerp_mode": "catmullrom"
						},
						"5.125": {
							"post": [1.91, 0.55, 0.35],
							"lerp_mode": "catmullrom"
						},
						"5.25": {
							"post": [-1, 0, 0],
							"lerp_mode": "catmullrom"
						},
						"5.375": {
							"post": [0.4, 0, 0],
							"lerp_mode": "catmullrom"
						},
						"5.5": {
							"post": [0, 0, 0],
							"lerp_mode": "catmullrom"
						}
					}
				}
			},
			"sound_effects": {
				"0.0": {
					"effect": "ex:mp5/mp5_inspect"
				}
			}
		},
		"inspect_empty": {
			"animation_length": 5.7917,
			"bones": {
				"root": {
					"rotation": {
						"0.0": [0, 0, 0],
						"0.0417": [-5.79, 0.13, 1.95],
						"0.1667": [-17.59, -10.78, -12.86],
						"0.25": [-25.6, -24.52, -35.41],
						"0.2917": [-27.59976, -27.22756, -41.19159],
						"0.3333": [-29.18247, -28.58725, -44.21775],
						"0.4167": [-31.13848, -27.68974, -42.19082],
						"0.5": [-30.66598, -28.14222, -43.20004],
						"0.5833": [-31.42, -28.14, -43.2],
						"0.7083": [-32.01, -27.44, -41.92],
						"0.9167": [-31.74, -28, -42.94],
						"1.0": [-31.76, -28.22, -43.36],
						"1.5": [-31.20393, -28.6466, -44.18009],
						"1.5417": [-29.85, -30.65, -48.19],
						"1.6667": [-29.18045, -31.65513, -50.18764],
						"1.7917": [-29.71221, -31.16351, -49.16731],
						"1.9583": [-29.71, -31.16, -49.17],
						"2.2083": [-29.1733, -31.63628, -50.20015],
						"2.2917": [-28.77, -30.86, -48.82],
						"2.4167": [-27.89, -26.22, -40.22],
						"2.4583": [-26.12, -16.94, -23.01],
						"2.5": [-27.22851, -1.49811, -0.30357],
						"2.6667": [-27.64133, 24.07175, 55.7761],
						"2.7917": [-27.55942, 24.18741, 56.01913],
						"2.9167": [-26.63512, 25.213, 58.2211],
						"3.0833": [-27.05095, 24.76144, 57.23672],
						"3.2917": [-27.18, 24.27, 56.94],
						"3.5": [-27.3, 24.11, 56.64],
						"3.75": [-27.43825, 24.30227, 56.26287],
						"3.9583": [-27.13612, 27.9047, 59.22256],
						"4.125": [-27.60586, 27.4605, 58.21082],
						"4.3333": [-27.25, 27.82, 58.99],
						"4.5417": [-27.1, 27.74, 59.31],
						"4.7083": [-26.95, 27.21, 59.62],
						"4.7917": [-26.5, 25.14, 57.6],
						"4.9167": [-25.69, 21.35, 53.37],
						"5.0": [-27.3, 13.08, 39.44],
						"5.1667": [-17.16969, -2.07286, 18.42359],
						"5.25": [9.41515, -1.03643, 9.2118],
						"5.375": [1.9612, -0.55625, 7.98076],
						"5.5": [0.66898, -0.48139, 1.31942],
						"5.5833": [-1.00521, -0.46117, 2.73757],
						"5.75": [0, 0, 0]
					},
					"position": {
						"0.0": [0, 0, 0],
						"0.0833": [-0.07, 0.63, 0],
						"0.1667": [-0.13, 1, 0],
						"0.25": [-0.51, 1.07, 0],
						"0.3333": {
							"pre": [-0.6, 1.3, 0],
							"post": [-0.8, 1.3, 0],
							"lerp_mode": "catmullrom"
						},
						"0.4583": {
							"post": [-0.8, 1.5, 0],
							"lerp_mode": "catmullrom"
						},
						"0.5417": {
							"post": [-0.8, 1.5, 0],
							"lerp_mode": "catmullrom"
						},
						"0.6667": {
							"post": [-0.8, 1.5, 0],
							"lerp_mode": "catmullrom"
						},
						"0.75": {
							"post": [-0.8, 1.5, 0],
							"lerp_mode": "catmullrom"
						},
						"0.8333": {
							"post": [-0.8, 1.5, 0],
							"lerp_mode": "catmullrom"
						},
						"1.0": [-0.8, 1.5, 0],
						"1.25": [-0.8, 1.5, 0],
						"1.5": [-0.8, 1.5, 0],
						"1.5833": {
							"pre": [-0.8, 1.5, 0],
							"post": [-1, 1.5, 0],
							"lerp_mode": "catmullrom"
						},
						"1.9583": {
							"post": [-0.8, 1.5, 0],
							"lerp_mode": "catmullrom"
						},
						"2.0417": {
							"post": [-0.8, 1.5, 0],
							"lerp_mode": "catmullrom"
						},
						"2.25": [-0.8, 1.5, 0],
						"2.3333": [-0.8, 1.5, 0],
						"2.4583": [0.35, 1.5, -0.9],
						"2.5833": [0.95, 1.7, -1.2],
						"2.75": [1.6, 2.38, -1.3],
						"2.8333": [1.6, 2.38, -1.3],
						"3.0": {
							"pre": [1.6, 2.38, -1.3],
							"post": [1.6, 2.38, -1.3],
							"lerp_mode": "catmullrom"
						},
						"3.2083": {
							"post": [1.6, 2.38, -1.3],
							"lerp_mode": "catmullrom"
						},
						"3.75": [1.6, 2.38, -1.3],
						"4.0417": [1.6, 2.38, -1.3],
						"4.3333": [1.6, 2.38, -1.3],
						"4.9583": [1.6, 2.38, -1.3],
						"5.0833": [0.48, 0.855, -1.12],
						"5.2083": [0, -0.5, -0.3],
						"5.5417": [0, 0, 0.22],
						"5.625": [0, -0.2, -0.17],
						"5.7917": [0, 0, 0]
					}
				},
				"lefthand": {
					"rotation": {
						"0.0": [111.54907, -25.87501, 174.37624],
						"5.25": [111.54907, -25.87501, 174.37624]
					},
					"position": {
						"0.0": [6.425, -13.1, -12.525],
						"0.5": [10.89, -15.62, 25.26],
						"2.25": [-3.11, -29.62, 25.26],
						"2.5": [6.8937, -12.62, -7.745],
						"4.9583": [6.8937, -12.62, -7.745],
						"5.25": [6.425, -13.1, -12.525]
					},
					"scale": {
						"0.0": [1, 1.5, 1],
						"0.5": [0, 0, 0],
						"2.25": [0, 0, 0],
						"2.4583": [1, 1, 1],
						"2.5": [1, 1.5, 1],
						"4.9583": [1, 1.5, 1]
					}
				},
				"righthand": {
					"rotation": [92.5, -355, -180],
					"position": [-6.25, -13.275, -1.7],
					"scale": [1, 1.5, 1]
				},
				"camera": {
					"rotation": {
						"0.0": {
							"post": [0, 0, 0],
							"lerp_mode": "catmullrom"
						},
						"0.0833": {
							"post": [2.38, 1.14, 0],
							"lerp_mode": "catmullrom"
						},
						"0.2083": {
							"post": [2.43, 2.29, 0],
							"lerp_mode": "catmullrom"
						},
						"0.2917": {
							"post": [1.29, 2.86, 0],
							"lerp_mode": "catmullrom"
						},
						"0.4167": {
							"post": [-1, 4, 0],
							"lerp_mode": "catmullrom"
						},
						"0.5833": {
							"post": [-2.00275, 4.99939, -0.03503],
							"lerp_mode": "catmullrom"
						},
						"0.9167": {
							"post": [-1.25, 5, -0.04],
							"lerp_mode": "catmullrom"
						},
						"1.2083": {
							"post": [-1.53, 5.54, -0.05],
							"lerp_mode": "catmullrom"
						},
						"1.4167": {
							"post": [-1.9, 5.77, -0.05],
							"lerp_mode": "catmullrom"
						},
						"1.7083": {
							"post": [-2.6, 6, -0.05],
							"lerp_mode": "catmullrom"
						},
						"1.9167": {
							"post": [-2.45, 6, -0.05],
							"lerp_mode": "catmullrom"
						},
						"2.0833": {
							"post": [-2.62, 6, -0.05],
							"lerp_mode": "catmullrom"
						},
						"2.25": {
							"post": [-3, 6, -0.05],
							"lerp_mode": "catmullrom"
						},
						"2.4167": {
							"post": [-0.74, 3.75, 0.02],
							"lerp_mode": "catmullrom"
						},
						"2.5": {
							"post": [0.26, 2.75, 0.06],
							"lerp_mode": "catmullrom"
						},
						"2.5833": {
							"post": [0.76, 2.25, 0.08],
							"lerp_mode": "catmullrom"
						},
						"2.7917": {
							"post": [1.76, 1.75, 0.08],
							"lerp_mode": "catmullrom"
						},
						"2.9167": {
							"post": [1.47, 1.75, 0.08],
							"lerp_mode": "catmullrom"
						},
						"3.0": {
							"post": [1.4, 1.75, 0.08],
							"lerp_mode": "catmullrom"
						},
						"3.1667": {
							"post": [1.32, 1.75, 0.08],
							"lerp_mode": "catmullrom"
						},
						"3.3333": {
							"post": [1.06, 1.75, 0.08],
							"lerp_mode": "catmullrom"
						},
						"3.7083": {
							"post": [0.36, 1.75, 0.08],
							"lerp_mode": "catmullrom"
						},
						"3.7917": {
							"post": [0.04, 1.75, 0.08],
							"lerp_mode": "catmullrom"
						},
						"3.9167": {
							"post": [-0.41, 1.75, 0.08],
							"lerp_mode": "catmullrom"
						},
						"4.0417": {
							"post": [-0.82, 1.75, 0.08],
							"lerp_mode": "catmullrom"
						},
						"4.4167": {
							"post": [-0.77, 1.75, 0.08],
							"lerp_mode": "catmullrom"
						},
						"4.5833": {
							"post": [-0.75, 1.75, 0.08],
							"lerp_mode": "catmullrom"
						},
						"4.7917": {
							"post": [-0.74, 1.75, 0.08],
							"lerp_mode": "catmullrom"
						},
						"4.9167": {
							"post": [1.29018, 1.7103, 1.07967],
							"lerp_mode": "catmullrom"
						},
						"5.0": {
							"post": [2.13, 1.06, 0.67],
							"lerp_mode": "catmullrom"
						},
						"5.125": {
							"post": [1.91, 0.55, 0.35],
							"lerp_mode": "catmullrom"
						},
						"5.25": {
							"post": [-1, 0, 0],
							"lerp_mode": "catmullrom"
						},
						"5.375": {
							"post": [0.4, 0, 0],
							"lerp_mode": "catmullrom"
						},
						"5.5": {
							"post": [0, 0, 0],
							"lerp_mode": "catmullrom"
						}
					}
				}
			},
			"sound_effects": {
				"0.0": {
					"effect": "ex:mp5/mp5_inspect"
				}
			}
		},
		"run": {
			"loop": true,
			"animation_length": 0.8,
			"bones": {
				"root": {
					"rotation": {
						"0.0": [-68.73, -5.5, -3.14],
						"0.05": [-68.99, -7.39, -3.57],
						"0.1": [-69.36, -9.11, -3.81],
						"0.15": [-69.45, -10.1, -3.75],
						"0.2": [-68.82, -9.82, -3.09],
						"0.25": [-67.92, -8.81, -2.13],
						"0.3": [-67.68, -8.15, -1.7],
						"0.35": [-68.9, -8.72, -2.46],
						"0.4": [-70.77, -9.63, -3.74],
						"0.45": [-71.87, -9.32, -4.34],
						"0.5": [-71.58, -7.25, -3.75],
						"0.55": [-70.7, -4.07, -2.59],
						"0.6": [-69.68, -1.04, -1.42],
						"0.65": [-68.98, 0.57, -0.8],
						"0.7": [-68.67, -0.33, -1.21],
						"0.75": [-68.65, -3, -2.27],
						"0.8": [-68.73, -5.5, -3.14]
					},
					"position": {
						"0.0": [-3.64, -0.38, -0.64],
						"0.05": [-3.63, -0.52, -0.64],
						"0.1": [-3.66, -0.87, -0.64],
						"0.15": [-3.67, -1.23, -0.64],
						"0.2": [-3.64, -1.38, -0.64],
						"0.25": [-3.52, -1.18, -0.64],
						"0.3": [-3.34, -0.78, -0.64],
						"0.35": [-3.19, -0.39, -0.64],
						"0.4": [-3.14, -0.23, -0.64],
						"0.45": [-3.26, -0.47, -0.64],
						"0.5": [-3.5, -0.94, -0.64],
						"0.55": [-3.74, -1.42, -0.64],
						"0.6": [-3.89, -1.64, -0.64],
						"0.65": [-3.89, -1.46, -0.64],
						"0.7": [-3.81, -1.04, -0.64],
						"0.75": [-3.71, -0.6, -0.64],
						"0.8": [-3.64, -0.38, -0.64]
					}
				},
				"lefthand_pos": {
					"position": [-14, -25, 15.5],
					"scale": 0
				},
				"camera": {
					"rotation": {
						"0.0": [0, 0, 0],
						"0.05": [0.09, 0, 0.15],
						"0.1": [0.13, 0, 0.25],
						"0.15": [-0.07, 0, 0.07],
						"0.2": [-0.25, 0, -0.12],
						"0.25": [-0.15, 0, -0.09],
						"0.3": [0, 0, 0],
						"0.35": [0.02, 0, 0.02],
						"0.4": [0, 0, 0],
						"0.45": [-0.01, 0, -0.08],
						"0.5": [0, 0, -0.12],
						"0.55": [0.08, 0, 0],
						"0.6": [0.13, 0, 0.13],
						"0.65": [0, 0, 0.08],
						"0.7": [-0.12, 0, 0],
						"0.75": [-0.09, 0, -0.02],
						"0.8": [0, 0, 0]
					}
				}
			}
		},
		"run_start": {
			"animation_length": 0.55,
			"bones": {
				"root": {
					"rotation": {
						"0.0": [0, 0, 0],
						"0.05": [2.8, -0.48, 3.97],
						"0.1": [5.79, -1.19, 9.23],
						"0.15": [1.73, -2.05, 11.57],
						"0.2": [-10.48, -2.9, 9.39],
						"0.25": [-28.47, -3.91, 4.94],
						"0.3": [-46.79, -4.85, 0.12],
						"0.35": [-59.98, -5.5, -3.14],
						"0.4": [-66.1, -5.75, -4.18],
						"0.45": [-68.22, -5.72, -4.06],
						"0.5": [-68.4, -5.59, -3.49],
						"0.55": [-68.73, -5.5, -3.14]
					},
					"position": {
						"0.0": [0, 0, 0],
						"0.05": [0.06, -0.64, -0.32],
						"0.1": [0.17, -1.58, -0.79],
						"0.15": [0.17, -2.44, -1.22],
						"0.2": [-0.09, -2.83, -1.45],
						"0.25": [-1.13, -2.25, -1.28],
						"0.3": [-2.54, -1.06, -0.83],
						"0.35": [-3.57, -0.19, -0.51],
						"0.4": [-3.83, -0.04, -0.47],
						"0.45": [-3.82, -0.12, -0.51],
						"0.5": [-3.71, -0.28, -0.59],
						"0.55": [-3.64, -0.38, -0.64]
					}
				},
				"lefthand_pos": {
					"position": {
						"0.0": [0, 0, 0],
						"0.1": [-7.17, -3.67, 0],
						"0.2": [-11.83, -12.08, 2],
						"0.3": [-14, -25, 15.5]
					},
					"scale": {
						"0.2": [1, 1, 1],
						"0.3": [0, 0, 0]
					}
				},
				"camera": {
					"rotation": {
						"0.0": {
							"post": [0, 0, 0],
							"lerp_mode": "catmullrom"
						},
						"0.1": {
							"post": [0.75, 0, -0.5],
							"lerp_mode": "catmullrom"
						},
						"0.2": {
							"post": [-0.25, 0, 0.1875],
							"lerp_mode": "catmullrom"
						},
						"0.3": {
							"post": [0, 0, 0],
							"lerp_mode": "catmullrom"
						},
						"0.4": {
							"post": [0, 0, 0],
							"lerp_mode": "catmullrom"
						}
					}
				}
			}
		},
		"run_end": {
			"animation_length": 0.65,
			"bones": {
				"root": {
					"rotation": {
						"0.0": [-68.73, -5.5, -3.14],
						"0.05": [-55.61, -4.21, 0.37],
						"0.1": [-36.44, -2.32, 5.59],
						"0.15": [-17.16, -0.44, 10.34],
						"0.2": [-3.66, 0.81, 12.47],
						"0.25": [1.72, 1.17, 10.52],
						"0.3": [2.4, 1, 5.92],
						"0.35": [1.03, 0.62, 0.91],
						"0.4": [0.28, 0.35, -2.3],
						"0.45": [0.49, 0.21, -2.71],
						"0.5": [0.23, 0.09, -1.23],
						"0.55": [0, 0, 0],
						"0.6": [-0.02, -0.02, 0.14],
						"0.65": [0, 0, 0]
					},
					"position": {
						"0.0": [-3.64, -0.38, -0.64],
						"0.05": [-2.73, -1.11, -1.21],
						"0.1": [-1.47, -2.08, -1.96],
						"0.15": [-0.5, -2.5, -2.25],
						"0.2": [-0.17, -2.06, -1.84],
						"0.25": [-0.04, -1.17, -1.06],
						"0.3": [-0.01, -0.24, -0.23],
						"0.35": [0.02, 0.37, 0.3],
						"0.4": [0.06, 0.47, 0.4],
						"0.45": [0.05, 0.22, 0.18],
						"0.5": [0.03, 0.01, -0.01],
						"0.55": [0.02, -0.02, -0.03],
						"0.6": [0.01, -0.01, -0.01],
						"0.65": [0, 0, 0]
					}
				},
				"lefthand_pos": {
					"position": {
						"0.0": [-14, -25, 15.5],
						"0.1": [-11.83, -12.08, 2],
						"0.2": [-7.17, -3.67, 0],
						"0.3": [0, 0, 0]
					},
					"scale": {
						"0.15": [0, 0, 0],
						"0.2": [1, 1, 1]
					}
				},
				"camera": {
					"rotation": {
						"0.25": {
							"pre": [0, 0, 0],
							"post": [0, 0, 0],
							"lerp_mode": "catmullrom"
						},
						"0.3": {
							"post": [0, 0, 0.3],
							"lerp_mode": "catmullrom"
						},
						"0.35": {
							"post": [0, 0, -0.125],
							"lerp_mode": "catmullrom"
						},
						"0.45": {
							"post": [0, 0, 0],
							"lerp_mode": "catmullrom"
						}
					}
				}
			}
		},
		"run_hold": {
			"animation_length": 0.2917,
			"bones": {
				"root": {
					"rotation": [-68.73314, -5.50468, -3.14473],
					"position": [-3.64, -0.38, -0.64]
				},
				"lefthand_pos": {
					"position": [-14, -25, 15.5],
					"scale": 0
				}
			}
		},
		"melee_stock": {
			"animation_length": 0.0333,
			"bones": {
				"root": {
					"rotation": [0, 0, 0],
					"position": [0, 0, 0]
				}
			}
		}
	}
}