{
	"format_version": "1.12.0",
	"minecraft:geometry": [
		{
			"description": {
				"identifier": "geometry.unknown",
				"texture_width": 512,
				"texture_height": 512,
				"visible_bounds_width": 2,
				"visible_bounds_height": 1.5,
				"visible_bounds_offset": [0, 0.25, 0]
			},
			"bones": [
				{
					"name": "dagger",
					"pivot": [0, -8, -1.125]
				},
				{
					"name": "blade",
					"parent": "dagger",
					"pivot": [0, -1.03661, -2.03908]
				},
				{
					"name": "grip",
					"parent": "dagger",
					"pivot": [0, -1.50001, 3.13393]
				},
				{
					"name": "bone3",
					"parent": "dagger",
					"pivot": [0, -9, -0.625]
				},
				{
					"name": "cid",
					"parent": "dagger",
					"pivot": [0, -2, 0.98438],
					"cubes": [
						{
							"origin": [-0.125, -2.92187, 1.1],
							"size": [0.25, 0.3125, 0.69688],
							"uv": {
								"north": {"uv": [27, 17], "uv_size": [0.5, 0.5]},
								"east": {"uv": [18, 27], "uv_size": [0.5, 0.5]},
								"south": {"uv": [27, 18], "uv_size": [0.5, 0.5]},
								"west": {"uv": [19, 27], "uv_size": [0.5, 0.5]},
								"up": {"uv": [27, 19], "uv_size": [0.5, 0.5]},
								"down": {"uv": [20, 27.5], "uv_size": [0.5, -0.5]}
							}
						},
						{
							"origin": [0.0625, -3.7451, 0.25],
							"size": [0.23928, 0.95895, 4.54688],
							"uv": {
								"north": {"uv": [25, 22], "uv_size": [0.5, 1]},
								"east": {"uv": [4, 4], "uv_size": [4.5, 1]},
								"south": {"uv": [23, 25], "uv_size": [0.5, 1]},
								"west": {"uv": [4, 5], "uv_size": [4.5, 1]},
								"up": {"uv": [10, 11], "uv_size": [0.5, 4.5]},
								"down": {"uv": [11, 15.5], "uv_size": [0.5, -4.5]}
							}
						},
						{
							"origin": [-0.06629, -2.93861, 1.1],
							"size": [0.25, 0.25, 0.69688],
							"pivot": [0.05871, -2.71986, 6.25],
							"rotation": [0, 0, -45],
							"uv": {
								"north": {"uv": [27, 20], "uv_size": [0.5, 0.5]},
								"east": {"uv": [21, 27], "uv_size": [0.5, 0.5]},
								"south": {"uv": [27, 21], "uv_size": [0.5, 0.5]},
								"west": {"uv": [22, 27], "uv_size": [0.5, 0.5]},
								"up": {"uv": [27, 22], "uv_size": [0.5, 0.5]},
								"down": {"uv": [23, 27.5], "uv_size": [0.5, -0.5]}
							}
						},
						{
							"origin": [-0.06629, -3.84264, 0.25],
							"size": [0.25, 0.25, 4.54688],
							"pivot": [0.05871, -3.81139, 5.25],
							"rotation": [0, 0, 45],
							"uv": {
								"north": {"uv": [27, 23], "uv_size": [0.5, 0.5]},
								"east": {"uv": [11, 1], "uv_size": [4.5, 0.5]},
								"south": {"uv": [24, 27], "uv_size": [0.5, 0.5]},
								"west": {"uv": [12, 2], "uv_size": [4.5, 0.5]},
								"up": {"uv": [12, 11], "uv_size": [0.5, 4.5]},
								"down": {"uv": [0, 17.5], "uv_size": [0.5, -4.5]}
							}
						},
						{
							"origin": [-0.30178, -3.7451, 0.25],
							"size": [0.23928, 0.95895, 4.54688],
							"uv": {
								"north": {"uv": [25, 23], "uv_size": [0.5, 1]},
								"east": {"uv": [4, 6], "uv_size": [4.5, 1]},
								"south": {"uv": [24, 25], "uv_size": [0.5, 1]},
								"west": {"uv": [4, 7], "uv_size": [4.5, 1]},
								"up": {"uv": [1, 13], "uv_size": [0.5, 4.5]},
								"down": {"uv": [13, 12.5], "uv_size": [0.5, -4.5]}
							}
						},
						{
							"origin": [-0.18371, -3.84264, 0.25],
							"size": [0.25, 0.25, 4.54688],
							"pivot": [-0.05871, -3.81139, 5.25],
							"rotation": [0, 0, -45],
							"uv": {
								"north": {"uv": [27, 24], "uv_size": [0.5, 0.5]},
								"east": {"uv": [12, 3], "uv_size": [4.5, 0.5]},
								"south": {"uv": [25, 27], "uv_size": [0.5, 0.5]},
								"west": {"uv": [13, 13], "uv_size": [4.5, 0.5]},
								"up": {"uv": [2, 14], "uv_size": [0.5, 4.5]},
								"down": {"uv": [3, 18.5], "uv_size": [0.5, -4.5]}
							}
						},
						{
							"origin": [-0.18371, -2.93861, 1.1],
							"size": [0.25, 0.25, 0.69688],
							"pivot": [-0.05871, -2.71986, 6.25],
							"rotation": [0, 0, 45],
							"uv": {
								"north": {"uv": [27, 25], "uv_size": [0.5, 0.5]},
								"east": {"uv": [26, 27], "uv_size": [0.5, 0.5]},
								"south": {"uv": [27, 26], "uv_size": [0.5, 0.5]},
								"west": {"uv": [27, 27], "uv_size": [0.5, 0.5]},
								"up": {"uv": [0, 28], "uv_size": [0.5, 0.5]},
								"down": {"uv": [28, 0.5], "uv_size": [0.5, -0.5]}
							}
						},
						{
							"origin": [-0.06629, -2.93861, 2.1],
							"size": [0.25, 0.25, 0.69688],
							"pivot": [0.05871, -2.71986, 7.25],
							"rotation": [0, 0, -45],
							"uv": {
								"north": {"uv": [1, 28], "uv_size": [0.5, 0.5]},
								"east": {"uv": [28, 1], "uv_size": [0.5, 0.5]},
								"south": {"uv": [2, 28], "uv_size": [0.5, 0.5]},
								"west": {"uv": [28, 2], "uv_size": [0.5, 0.5]},
								"up": {"uv": [3, 28], "uv_size": [0.5, 0.5]},
								"down": {"uv": [28, 3.5], "uv_size": [0.5, -0.5]}
							}
						},
						{
							"origin": [-0.18371, -2.93861, 2.1],
							"size": [0.25, 0.25, 0.69688],
							"pivot": [-0.05871, -2.71986, 7.25],
							"rotation": [0, 0, 45],
							"uv": {
								"north": {"uv": [4, 28], "uv_size": [0.5, 0.5]},
								"east": {"uv": [28, 4], "uv_size": [0.5, 0.5]},
								"south": {"uv": [5, 28], "uv_size": [0.5, 0.5]},
								"west": {"uv": [28, 5], "uv_size": [0.5, 0.5]},
								"up": {"uv": [6, 28], "uv_size": [0.5, 0.5]},
								"down": {"uv": [28, 6.5], "uv_size": [0.5, -0.5]}
							}
						},
						{
							"origin": [-0.125, -2.92187, 2.1],
							"size": [0.25, 0.3125, 0.69688],
							"uv": {
								"north": {"uv": [7, 28], "uv_size": [0.5, 0.5]},
								"east": {"uv": [28, 7], "uv_size": [0.5, 0.5]},
								"south": {"uv": [8, 28], "uv_size": [0.5, 0.5]},
								"west": {"uv": [28, 8], "uv_size": [0.5, 0.5]},
								"up": {"uv": [9, 28], "uv_size": [0.5, 0.5]},
								"down": {"uv": [28, 9.5], "uv_size": [0.5, -0.5]}
							}
						},
						{
							"origin": [-0.06629, -2.93861, 3.1],
							"size": [0.25, 0.25, 0.69688],
							"pivot": [0.05871, -2.71986, 8.25],
							"rotation": [0, 0, -45],
							"uv": {
								"north": {"uv": [10, 28], "uv_size": [0.5, 0.5]},
								"east": {"uv": [28, 10], "uv_size": [0.5, 0.5]},
								"south": {"uv": [11, 28], "uv_size": [0.5, 0.5]},
								"west": {"uv": [28, 11], "uv_size": [0.5, 0.5]},
								"up": {"uv": [12, 28], "uv_size": [0.5, 0.5]},
								"down": {"uv": [28, 12.5], "uv_size": [0.5, -0.5]}
							}
						},
						{
							"origin": [-0.18371, -2.93861, 3.1],
							"size": [0.25, 0.25, 0.69688],
							"pivot": [-0.05871, -2.71986, 8.25],
							"rotation": [0, 0, 45],
							"uv": {
								"north": {"uv": [13, 28], "uv_size": [0.5, 0.5]},
								"east": {"uv": [28, 13], "uv_size": [0.5, 0.5]},
								"south": {"uv": [14, 28], "uv_size": [0.5, 0.5]},
								"west": {"uv": [28, 14], "uv_size": [0.5, 0.5]},
								"up": {"uv": [15, 28], "uv_size": [0.5, 0.5]},
								"down": {"uv": [28, 15.5], "uv_size": [0.5, -0.5]}
							}
						},
						{
							"origin": [-0.125, -2.92187, 3.1],
							"size": [0.25, 0.3125, 0.69688],
							"uv": {
								"north": {"uv": [16, 28], "uv_size": [0.5, 0.5]},
								"east": {"uv": [28, 16], "uv_size": [0.5, 0.5]},
								"south": {"uv": [17, 28], "uv_size": [0.5, 0.5]},
								"west": {"uv": [28, 17], "uv_size": [0.5, 0.5]},
								"up": {"uv": [18, 28], "uv_size": [0.5, 0.5]},
								"down": {"uv": [28, 18.5], "uv_size": [0.5, -0.5]}
							}
						},
						{
							"origin": [-0.06629, -2.93861, 0.25],
							"size": [0.25, 0.25, 0.54688],
							"pivot": [0.05871, -2.71986, 5.25],
							"rotation": [0, 0, -45],
							"uv": {
								"north": {"uv": [19, 28], "uv_size": [0.5, 0.5]},
								"east": {"uv": [28, 19], "uv_size": [0.5, 0.5]},
								"south": {"uv": [20, 28], "uv_size": [0.5, 0.5]},
								"west": {"uv": [28, 20], "uv_size": [0.5, 0.5]},
								"up": {"uv": [21, 28], "uv_size": [0.5, 0.5]},
								"down": {"uv": [28, 21.5], "uv_size": [0.5, -0.5]}
							}
						},
						{
							"origin": [-0.125, -3.92187, 0.25],
							"size": [0.25, 1.3125, 0.54688],
							"uv": {
								"north": {"uv": [23, 8], "uv_size": [0.5, 1.5]},
								"east": {"uv": [10, 23], "uv_size": [0.5, 1.5]},
								"south": {"uv": [23, 10], "uv_size": [0.5, 1.5]},
								"west": {"uv": [12, 23], "uv_size": [0.5, 1.5]},
								"up": {"uv": [22, 28], "uv_size": [0.5, 0.5]},
								"down": {"uv": [28, 22.5], "uv_size": [0.5, -0.5]}
							}
						},
						{
							"origin": [-0.18371, -2.93861, 0.25],
							"size": [0.25, 0.25, 0.54688],
							"pivot": [-0.05871, -2.71986, 5.25],
							"rotation": [0, 0, 45],
							"uv": {
								"north": {"uv": [23, 28], "uv_size": [0.5, 0.5]},
								"east": {"uv": [28, 23], "uv_size": [0.5, 0.5]},
								"south": {"uv": [24, 28], "uv_size": [0.5, 0.5]},
								"west": {"uv": [28, 24], "uv_size": [0.5, 0.5]},
								"up": {"uv": [25, 28], "uv_size": [0.5, 0.5]},
								"down": {"uv": [28, 25.5], "uv_size": [0.5, -0.5]}
							}
						},
						{
							"origin": [-0.06629, -2.93861, 0.775],
							"size": [0.25, 0.225, 3.29688],
							"pivot": [0.05871, -2.74486, 5.775],
							"rotation": [0, 0, -45],
							"uv": {
								"north": {"uv": [26, 28], "uv_size": [0.5, 0.5]},
								"east": {"uv": [17, 4], "uv_size": [3.5, 0.5]},
								"south": {"uv": [28, 26], "uv_size": [0.5, 0.5]},
								"west": {"uv": [17, 5], "uv_size": [3.5, 0.5]},
								"up": {"uv": [9, 17], "uv_size": [0.5, 3.5]},
								"down": {"uv": [11, 20.5], "uv_size": [0.5, -3.5]}
							}
						},
						{
							"origin": [-0.125, -2.94687, 0.775],
							"size": [0.25, 0.3125, 3.29688],
							"uv": {
								"north": {"uv": [27, 28], "uv_size": [0.5, 0.5]},
								"east": {"uv": [17, 16], "uv_size": [3.5, 0.5]},
								"south": {"uv": [28, 27], "uv_size": [0.5, 0.5]},
								"west": {"uv": [17, 17], "uv_size": [3.5, 0.5]},
								"up": {"uv": [12, 17], "uv_size": [0.5, 3.5]},
								"down": {"uv": [13, 20.5], "uv_size": [0.5, -3.5]}
							}
						},
						{
							"origin": [-0.18371, -2.93861, 0.775],
							"size": [0.25, 0.225, 3.29688],
							"pivot": [-0.05871, -2.74486, 5.775],
							"rotation": [0, 0, 45],
							"uv": {
								"north": {"uv": [28, 28], "uv_size": [0.5, 0.5]},
								"east": {"uv": [18, 7], "uv_size": [3.5, 0.5]},
								"south": {"uv": [0, 29], "uv_size": [0.5, 0.5]},
								"west": {"uv": [18, 8], "uv_size": [3.5, 0.5]},
								"up": {"uv": [14, 17], "uv_size": [0.5, 3.5]},
								"down": {"uv": [0, 21.5], "uv_size": [0.5, -3.5]}
							}
						},
						{
							"origin": [-0.06629, -2.93861, 4.25],
							"size": [0.25, 0.25, 0.54688],
							"pivot": [0.05871, -2.71986, 9.25],
							"rotation": [0, 0, -45],
							"uv": {
								"north": {"uv": [29, 0], "uv_size": [0.5, 0.5]},
								"east": {"uv": [1, 29], "uv_size": [0.5, 0.5]},
								"south": {"uv": [29, 1], "uv_size": [0.5, 0.5]},
								"west": {"uv": [2, 29], "uv_size": [0.5, 0.5]},
								"up": {"uv": [29, 2], "uv_size": [0.5, 0.5]},
								"down": {"uv": [3, 29.5], "uv_size": [0.5, -0.5]}
							}
						},
						{
							"origin": [-0.125, -3.92187, 0.79063],
							"size": [0.25, 0.6125, 4.02813],
							"uv": {
								"north": {"uv": [29, 3], "uv_size": [0.5, 0.5]},
								"east": {"uv": [16, 1], "uv_size": [4, 0.5]},
								"south": {"uv": [4, 29], "uv_size": [0.5, 0.5]},
								"west": {"uv": [16, 6], "uv_size": [4, 0.5]},
								"up": {"uv": [16, 7], "uv_size": [0.5, 4]},
								"down": {"uv": [10, 20], "uv_size": [0.5, -4]}
							}
						},
						{
							"origin": [-0.125, -2.92187, 4.26563],
							"size": [0.25, 0.3125, 0.54688],
							"uv": {
								"north": {"uv": [29, 4], "uv_size": [0.5, 0.5]},
								"east": {"uv": [5, 29], "uv_size": [0.5, 0.5]},
								"south": {"uv": [29, 5], "uv_size": [0.5, 0.5]},
								"west": {"uv": [6, 29], "uv_size": [0.5, 0.5]},
								"up": {"uv": [29, 6], "uv_size": [0.5, 0.5]},
								"down": {"uv": [7, 29.5], "uv_size": [0.5, -0.5]}
							}
						},
						{
							"origin": [-0.18371, -2.93861, 4.25],
							"size": [0.25, 0.25, 0.54688],
							"pivot": [-0.05871, -2.71986, 9.25],
							"rotation": [0, 0, 45],
							"uv": {
								"north": {"uv": [29, 7], "uv_size": [0.5, 0.5]},
								"east": {"uv": [8, 29], "uv_size": [0.5, 0.5]},
								"south": {"uv": [29, 8], "uv_size": [0.5, 0.5]},
								"west": {"uv": [9, 29], "uv_size": [0.5, 0.5]},
								"up": {"uv": [29, 9], "uv_size": [0.5, 0.5]},
								"down": {"uv": [10, 29.5], "uv_size": [0.5, -0.5]}
							}
						},
						{
							"origin": [-0.06629, -2.93861, 3.75],
							"size": [0.25, 0.25, 0.54688],
							"pivot": [0.05871, -2.71986, 8.75],
							"rotation": [0, 0, -45],
							"uv": {
								"north": {"uv": [29, 10], "uv_size": [0.5, 0.5]},
								"east": {"uv": [11, 29], "uv_size": [0.5, 0.5]},
								"south": {"uv": [29, 11], "uv_size": [0.5, 0.5]},
								"west": {"uv": [12, 29], "uv_size": [0.5, 0.5]},
								"up": {"uv": [29, 12], "uv_size": [0.5, 0.5]},
								"down": {"uv": [13, 29.5], "uv_size": [0.5, -0.5]}
							}
						},
						{
							"origin": [-0.125, -2.92187, 3.75],
							"size": [0.25, 0.3125, 0.54688],
							"uv": {
								"north": {"uv": [29, 13], "uv_size": [0.5, 0.5]},
								"east": {"uv": [14, 29], "uv_size": [0.5, 0.5]},
								"south": {"uv": [29, 14], "uv_size": [0.5, 0.5]},
								"west": {"uv": [15, 29], "uv_size": [0.5, 0.5]},
								"up": {"uv": [29, 15], "uv_size": [0.5, 0.5]},
								"down": {"uv": [16, 29.5], "uv_size": [0.5, -0.5]}
							}
						},
						{
							"origin": [-0.18371, -2.93861, 3.75],
							"size": [0.25, 0.25, 0.54688],
							"pivot": [-0.05871, -2.71986, 8.75],
							"rotation": [0, 0, 45],
							"uv": {
								"north": {"uv": [29, 16], "uv_size": [0.5, 0.5]},
								"east": {"uv": [17, 29], "uv_size": [0.5, 0.5]},
								"south": {"uv": [29, 17], "uv_size": [0.5, 0.5]},
								"west": {"uv": [18, 29], "uv_size": [0.5, 0.5]},
								"up": {"uv": [29, 18], "uv_size": [0.5, 0.5]},
								"down": {"uv": [19, 29.5], "uv_size": [0.5, -0.5]}
							}
						},
						{
							"origin": [0.0625, -3.7451, 4.79688],
							"size": [0.23928, 0.95895, 1.375],
							"uv": {
								"north": {"uv": [25, 24], "uv_size": [0.5, 1]},
								"east": {"uv": [19, 0], "uv_size": [1.5, 1]},
								"south": {"uv": [25, 25], "uv_size": [0.5, 1]},
								"west": {"uv": [4, 19], "uv_size": [1.5, 1]},
								"up": {"uv": [13, 23], "uv_size": [0.5, 1.5]},
								"down": {"uv": [23, 14.5], "uv_size": [0.5, -1.5]}
							}
						},
						{
							"origin": [-0.06629, -2.93861, 4.79688],
							"size": [0.25, 0.25, 1.375],
							"pivot": [0.05871, -2.71986, 6.5],
							"rotation": [0, 0, -45],
							"uv": {
								"north": {"uv": [29, 19], "uv_size": [0.5, 0.5]},
								"east": {"uv": [15, 23], "uv_size": [1.5, 0.5]},
								"south": {"uv": [20, 29], "uv_size": [0.5, 0.5]},
								"west": {"uv": [23, 19], "uv_size": [1.5, 0.5]},
								"up": {"uv": [23, 21], "uv_size": [0.5, 1.5]},
								"down": {"uv": [22, 24.5], "uv_size": [0.5, -1.5]}
							}
						},
						{
							"origin": [-0.06629, -3.84264, 4.90625],
							"size": [0.25, 0.25, 1.26563],
							"pivot": [0.05871, -3.81139, 6.5],
							"rotation": [0, 0, 45],
							"uv": {
								"north": {"uv": [29, 20], "uv_size": [0.5, 0.5]},
								"east": {"uv": [23, 23], "uv_size": [1.5, 0.5]},
								"south": {"uv": [21, 29], "uv_size": [0.5, 0.5]},
								"west": {"uv": [24, 0], "uv_size": [1.5, 0.5]},
								"up": {"uv": [3, 24], "uv_size": [0.5, 1.5]},
								"down": {"uv": [4, 25.5], "uv_size": [0.5, -1.5]}
							}
						},
						{
							"origin": [-0.18371, -3.84264, 4.90625],
							"size": [0.25, 0.25, 1.26563],
							"pivot": [-0.05871, -3.81139, 6.5],
							"rotation": [0, 0, -45],
							"uv": {
								"north": {"uv": [29, 21], "uv_size": [0.5, 0.5]},
								"east": {"uv": [24, 1], "uv_size": [1.5, 0.5]},
								"south": {"uv": [22, 29], "uv_size": [0.5, 0.5]},
								"west": {"uv": [24, 4], "uv_size": [1.5, 0.5]},
								"up": {"uv": [5, 24], "uv_size": [0.5, 1.5]},
								"down": {"uv": [24, 6.5], "uv_size": [0.5, -1.5]}
							}
						},
						{
							"origin": [-0.30178, -3.7451, 4.79688],
							"size": [0.23928, 0.95895, 1.375],
							"uv": {
								"north": {"uv": [0, 26], "uv_size": [0.5, 1]},
								"east": {"uv": [19, 12], "uv_size": [1.5, 1]},
								"south": {"uv": [26, 0], "uv_size": [0.5, 1]},
								"west": {"uv": [18, 19], "uv_size": [1.5, 1]},
								"up": {"uv": [7, 24], "uv_size": [0.5, 1.5]},
								"down": {"uv": [24, 8.5], "uv_size": [0.5, -1.5]}
							}
						},
						{
							"origin": [-0.18371, -2.93861, 4.79688],
							"size": [0.25, 0.25, 1.375],
							"pivot": [-0.05871, -2.71986, 6.5],
							"rotation": [0, 0, 45],
							"uv": {
								"north": {"uv": [29, 22], "uv_size": [0.5, 0.5]},
								"east": {"uv": [8, 24], "uv_size": [1.5, 0.5]},
								"south": {"uv": [23, 29], "uv_size": [0.5, 0.5]},
								"west": {"uv": [24, 9], "uv_size": [1.5, 0.5]},
								"up": {"uv": [24, 10], "uv_size": [0.5, 1.5]},
								"down": {"uv": [11, 25.5], "uv_size": [0.5, -1.5]}
							}
						},
						{
							"origin": [-0.125, -3.92187, 4.8125],
							"size": [0.25, 1.3125, 1.35938],
							"uv": {
								"north": {"uv": [24, 12], "uv_size": [0.5, 1.5]},
								"east": {"uv": [14, 8], "uv_size": [1.5, 1.5]},
								"south": {"uv": [14, 24], "uv_size": [0.5, 1.5]},
								"west": {"uv": [14, 10], "uv_size": [1.5, 1.5]},
								"up": {"uv": [24, 14], "uv_size": [0.5, 1.5]},
								"down": {"uv": [15, 25.5], "uv_size": [0.5, -1.5]}
							}
						},
						{
							"origin": [-0.125, -4.17187, 4.92188],
							"size": [0.25, 0.25, 1.25],
							"pivot": [0, -3.92187, 6.17188],
							"rotation": [-10, 0, 0],
							"uv": {
								"north": {"uv": [29, 23], "uv_size": [0.5, 0.5]},
								"east": {"uv": [16, 24], "uv_size": [1.5, 0.5]},
								"south": {"uv": [24, 29], "uv_size": [0.5, 0.5]},
								"west": {"uv": [24, 16], "uv_size": [1.5, 0.5]},
								"up": {"uv": [24, 17], "uv_size": [0.5, 1.5]},
								"down": {"uv": [18, 25.5], "uv_size": [0.5, -1.5]}
							}
						},
						{
							"origin": [-0.30446, -3.99399, 4.75],
							"size": [0.24196, 0.24399, 1.39062],
							"pivot": [0, -3.92187, 6.17188],
							"rotation": [-10, 0, 0],
							"uv": {
								"north": {"uv": [29, 24], "uv_size": [0.5, 0.5]},
								"east": {"uv": [19, 24], "uv_size": [1.5, 0.5]},
								"south": {"uv": [25, 29], "uv_size": [0.5, 0.5]},
								"west": {"uv": [24, 20], "uv_size": [1.5, 0.5]},
								"up": {"uv": [21, 24], "uv_size": [0.5, 1.5]},
								"down": {"uv": [24, 22.5], "uv_size": [0.5, -1.5]}
							}
						},
						{
							"origin": [0.0625, -3.99399, 4.75],
							"size": [0.24196, 0.24399, 1.39062],
							"pivot": [0, -3.92187, 6.17188],
							"rotation": [-10, 0, 0],
							"uv": {
								"north": {"uv": [29, 25], "uv_size": [0.5, 0.5]},
								"east": {"uv": [23, 24], "uv_size": [1.5, 0.5]},
								"south": {"uv": [26, 29], "uv_size": [0.5, 0.5]},
								"west": {"uv": [0, 25], "uv_size": [1.5, 0.5]},
								"up": {"uv": [2, 25], "uv_size": [0.5, 1.5]},
								"down": {"uv": [25, 3.5], "uv_size": [0.5, -1.5]}
							}
						},
						{
							"origin": [-0.375, -4.17567, 4.70659],
							"size": [0.25, 0.25, 1.40625],
							"pivot": [-0.125, -4.17187, 6.17188],
							"rotation": [-7.10708, 7.05302, 44.56145],
							"uv": {
								"north": {"uv": [29, 26], "uv_size": [0.5, 0.5]},
								"east": {"uv": [25, 5], "uv_size": [1.5, 0.5]},
								"south": {"uv": [27, 29], "uv_size": [0.5, 0.5]},
								"west": {"uv": [25, 6], "uv_size": [1.5, 0.5]},
								"up": {"uv": [6, 25], "uv_size": [0.5, 1.5]},
								"down": {"uv": [25, 8.5], "uv_size": [0.5, -1.5]}
							}
						},
						{
							"origin": [0.125, -4.17567, 4.70659],
							"size": [0.25, 0.25, 1.40625],
							"pivot": [0.125, -4.17187, 6.17188],
							"rotation": [-7.10708, -7.05302, -44.56145],
							"uv": {
								"north": {"uv": [29, 27], "uv_size": [0.5, 0.5]},
								"east": {"uv": [8, 25], "uv_size": [1.5, 0.5]},
								"south": {"uv": [28, 29], "uv_size": [0.5, 0.5]},
								"west": {"uv": [25, 10], "uv_size": [1.5, 0.5]},
								"up": {"uv": [10, 25], "uv_size": [0.5, 1.5]},
								"down": {"uv": [25, 12.5], "uv_size": [0.5, -1.5]}
							}
						},
						{
							"origin": [-0.31415, -4.10937, 0.04003],
							"size": [0.64274, 2.15954, 0.25684],
							"uv": {
								"north": {"uv": [7, 22], "uv_size": [0.5, 2]},
								"east": {"uv": [22, 7], "uv_size": [0.5, 2]},
								"south": {"uv": [22, 9], "uv_size": [0.5, 2]},
								"west": {"uv": [11, 22], "uv_size": [0.5, 2]},
								"up": {"uv": [29, 28], "uv_size": [0.5, 0.5]},
								"down": {"uv": [29, 29.5], "uv_size": [0.5, -0.5]}
							}
						},
						{
							"origin": [-0.20205, -4.28346, 0.04003],
							"size": [0.41972, 0.14613, 0.25684],
							"uv": {
								"north": {"uv": [0, 30], "uv_size": [0.5, 0.5]},
								"east": {"uv": [30, 0], "uv_size": [0.5, 0.5]},
								"south": {"uv": [1, 30], "uv_size": [0.5, 0.5]},
								"west": {"uv": [30, 1], "uv_size": [0.5, 0.5]},
								"up": {"uv": [2, 30], "uv_size": [0.5, 0.5]},
								"down": {"uv": [30, 2.5], "uv_size": [0.5, -0.5]}
							}
						},
						{
							"origin": [-1.23155, -3.7521, 0.04003],
							"size": [0.28336, 0.20642, 0.25684],
							"pivot": [-1.27677, -6.01773, -1.01562],
							"rotation": [0, 0, 32.5],
							"uv": {
								"north": {"uv": [3, 30], "uv_size": [0.5, 0.5]},
								"east": {"uv": [30, 3], "uv_size": [0.5, 0.5]},
								"south": {"uv": [4, 30], "uv_size": [0.5, 0.5]},
								"west": {"uv": [30, 4], "uv_size": [0.5, 0.5]},
								"up": {"uv": [5, 30], "uv_size": [0.5, 0.5]},
								"down": {"uv": [30, 5.5], "uv_size": [0.5, -0.5]}
							}
						},
						{
							"origin": [0.96381, -3.7521, 0.04003],
							"size": [0.26774, 0.20642, 0.25684],
							"pivot": [1.29239, -6.01773, -1.01562],
							"rotation": [0, 0, -32.5],
							"uv": {
								"north": {"uv": [6, 30], "uv_size": [0.5, 0.5]},
								"east": {"uv": [30, 6], "uv_size": [0.5, 0.5]},
								"south": {"uv": [7, 30], "uv_size": [0.5, 0.5]},
								"west": {"uv": [30, 7], "uv_size": [0.5, 0.5]},
								"up": {"uv": [8, 30], "uv_size": [0.5, 0.5]},
								"down": {"uv": [30, 8.5], "uv_size": [0.5, -0.5]}
							}
						}
					]
				},
				{
					"name": "bone6_illuminated",
					"parent": "cid",
					"pivot": [0.146, 0.3, -3.7],
					"cubes": [
						{
							"origin": [-0.03125, -2.77276, -13.7875],
							"size": [0.0625, 0.21875, 10.70625],
							"pivot": [0.146, 0.8, -3.7],
							"rotation": [1, 0, 0],
							"uv": {
								"north": {"uv": [9, 30], "uv_size": [0.5, 0.5]},
								"east": {"uv": [0, 0], "uv_size": [10.5, 0.5]},
								"south": {"uv": [30, 9], "uv_size": [0.5, 0.5]},
								"west": {"uv": [0, 1], "uv_size": [10.5, 0.5]},
								"up": {"uv": [0, 2], "uv_size": [0.5, 10.5]},
								"down": {"uv": [1, 12.5], "uv_size": [0.5, -10.5]}
							}
						},
						{
							"origin": [-0.03125, -3.07276, -13.0125],
							"size": [0.0625, 0.31875, 9.83125],
							"pivot": [0.146, 0.6, -3.7],
							"rotation": [1, 0, 0],
							"uv": {
								"north": {"uv": [10, 30], "uv_size": [0.5, 0.5]},
								"east": {"uv": [2, 2], "uv_size": [10, 0.5]},
								"south": {"uv": [30, 10], "uv_size": [0.5, 0.5]},
								"west": {"uv": [2, 3], "uv_size": [10, 0.5]},
								"up": {"uv": [2, 4], "uv_size": [0.5, 10]},
								"down": {"uv": [3, 14], "uv_size": [0.5, -10]}
							}
						},
						{
							"origin": [-0.03125, -3.37276, -12.3875],
							"size": [0.0625, 0.31875, 6.90625],
							"pivot": [0.146, 0.3, -3.7],
							"rotation": [1, 0, 0],
							"uv": {
								"north": {"uv": [11, 30], "uv_size": [0.5, 0.5]},
								"east": {"uv": [9, 6], "uv_size": [7, 0.5]},
								"south": {"uv": [30, 11], "uv_size": [0.5, 0.5]},
								"west": {"uv": [9, 7], "uv_size": [7, 0.5]},
								"up": {"uv": [8, 10], "uv_size": [0.5, 7]},
								"down": {"uv": [9, 17], "uv_size": [0.5, -7]}
							}
						},
						{
							"origin": [-0.03125, -5.84776, -3.6875],
							"size": [0.0625, 0.16875, 0.50625],
							"pivot": [0.146, -2.175, -1.5],
							"rotation": [-44, 0, 0],
							"uv": {
								"north": {"uv": [12, 30], "uv_size": [0.5, 0.5]},
								"east": {"uv": [30, 12], "uv_size": [0.5, 0.5]},
								"south": {"uv": [13, 30], "uv_size": [0.5, 0.5]},
								"west": {"uv": [30, 13], "uv_size": [0.5, 0.5]},
								"up": {"uv": [14, 30], "uv_size": [0.5, 0.5]},
								"down": {"uv": [30, 14.5], "uv_size": [0.5, -0.5]}
							}
						},
						{
							"origin": [-0.03125, -3.77276, -11.8875],
							"size": [0.0625, 0.41875, 8.40625],
							"pivot": [0.146, 0, -3.7],
							"rotation": [1, 0, 0],
							"uv": {
								"north": {"uv": [15, 30], "uv_size": [0.5, 0.5]},
								"east": {"uv": [4, 8], "uv_size": [8.5, 0.5]},
								"south": {"uv": [30, 15], "uv_size": [0.5, 0.5]},
								"west": {"uv": [4, 9], "uv_size": [8.5, 0.5]},
								"up": {"uv": [4, 10], "uv_size": [0.5, 8.5]},
								"down": {"uv": [5, 18.5], "uv_size": [0.5, -8.5]}
							}
						},
						{
							"origin": [-0.03125, -4.17276, -10.5875],
							"size": [0.0625, 0.41875, 7.30625],
							"pivot": [0.146, -0.4, -3.7],
							"rotation": [1, 0, 0],
							"uv": {
								"north": {"uv": [16, 30], "uv_size": [0.5, 0.5]},
								"east": {"uv": [9, 4], "uv_size": [7.5, 0.5]},
								"south": {"uv": [30, 16], "uv_size": [0.5, 0.5]},
								"west": {"uv": [9, 5], "uv_size": [7.5, 0.5]},
								"up": {"uv": [6, 10], "uv_size": [0.5, 7.5]},
								"down": {"uv": [7, 17.5], "uv_size": [0.5, -7.5]}
							}
						},
						{
							"origin": [-0.03125, -4.17276, -3.2875],
							"size": [0.0625, 0.21875, 1.70625],
							"uv": {
								"north": {"uv": [17, 30], "uv_size": [0.5, 0.5]},
								"east": {"uv": [12, 25], "uv_size": [1.5, 0.5]},
								"south": {"uv": [30, 17], "uv_size": [0.5, 0.5]},
								"west": {"uv": [25, 13], "uv_size": [1.5, 0.5]},
								"up": {"uv": [25, 14], "uv_size": [0.5, 1.5]},
								"down": {"uv": [16, 26.5], "uv_size": [0.5, -1.5]}
							}
						},
						{
							"origin": [-0.03125, -4.02276, -3.7375],
							"size": [0.0625, 0.24375, 2.55625],
							"uv": {
								"north": {"uv": [18, 30], "uv_size": [0.5, 0.5]},
								"east": {"uv": [20, 11], "uv_size": [2.5, 0.5]},
								"south": {"uv": [30, 18], "uv_size": [0.5, 0.5]},
								"west": {"uv": [18, 20], "uv_size": [2.5, 0.5]},
								"up": {"uv": [16, 20], "uv_size": [0.5, 2.5]},
								"down": {"uv": [21, 4.5], "uv_size": [0.5, -2.5]}
							}
						},
						{
							"origin": [-0.03125, -4.93897, -1.03893],
							"size": [0.0625, 0.21875, 0.70625],
							"uv": {
								"north": {"uv": [19, 30], "uv_size": [0.5, 0.5]},
								"east": {"uv": [30, 19], "uv_size": [0.5, 0.5]},
								"south": {"uv": [20, 30], "uv_size": [0.5, 0.5]},
								"west": {"uv": [30, 20], "uv_size": [0.5, 0.5]},
								"up": {"uv": [21, 30], "uv_size": [0.5, 0.5]},
								"down": {"uv": [30, 21.5], "uv_size": [0.5, -0.5]}
							}
						},
						{
							"origin": [-0.03125, -4.52276, -2.0125],
							"size": [0.0625, 0.51875, 1.20625],
							"pivot": [0.146, -4.45, -1.425],
							"rotation": [-45, 0, 0],
							"uv": {
								"north": {"uv": [22, 30], "uv_size": [0.5, 0.5]},
								"east": {"uv": [1, 26], "uv_size": [1, 0.5]},
								"south": {"uv": [30, 22], "uv_size": [0.5, 0.5]},
								"west": {"uv": [26, 1], "uv_size": [1, 0.5]},
								"up": {"uv": [26, 2], "uv_size": [0.5, 1]},
								"down": {"uv": [3, 27], "uv_size": [0.5, -1]}
							}
						},
						{
							"origin": [-0.03125, -4.27276, -0.8625],
							"size": [0.0625, 0.26875, 0.25625],
							"pivot": [0.146, -4.45, -1.425],
							"rotation": [-45, 0, 0],
							"uv": {
								"north": {"uv": [23, 30], "uv_size": [0.5, 0.5]},
								"east": {"uv": [30, 23], "uv_size": [0.5, 0.5]},
								"south": {"uv": [24, 30], "uv_size": [0.5, 0.5]},
								"west": {"uv": [30, 24], "uv_size": [0.5, 0.5]},
								"up": {"uv": [25, 30], "uv_size": [0.5, 0.5]},
								"down": {"uv": [30, 25.5], "uv_size": [0.5, -0.5]}
							}
						},
						{
							"origin": [-0.03125, -4.52276, -3.39375],
							"size": [0.0625, 0.51875, 0.60625],
							"pivot": [0.146, -4.45, -3.375],
							"rotation": [45, 0, 0],
							"uv": {
								"north": {"uv": [26, 30], "uv_size": [0.5, 0.5]},
								"east": {"uv": [30, 26], "uv_size": [0.5, 0.5]},
								"south": {"uv": [27, 30], "uv_size": [0.5, 0.5]},
								"west": {"uv": [30, 27], "uv_size": [0.5, 0.5]},
								"up": {"uv": [28, 30], "uv_size": [0.5, 0.5]},
								"down": {"uv": [30, 28.5], "uv_size": [0.5, -0.5]}
							}
						},
						{
							"origin": [-0.03125, -4.40917, -3.91979],
							"size": [0.0625, 0.21875, 0.88125],
							"pivot": [0.146, -4.33641, -3.62604],
							"rotation": [-50, 0, 0],
							"uv": {
								"north": {"uv": [29, 30], "uv_size": [0.5, 0.5]},
								"east": {"uv": [26, 3], "uv_size": [1, 0.5]},
								"south": {"uv": [30, 29], "uv_size": [0.5, 0.5]},
								"west": {"uv": [4, 26], "uv_size": [1, 0.5]},
								"up": {"uv": [26, 4], "uv_size": [0.5, 1]},
								"down": {"uv": [5, 27], "uv_size": [0.5, -1]}
							}
						},
						{
							"origin": [-0.03125, -4.91723, -3.41006],
							"size": [0.0625, 0.21875, 0.30625],
							"pivot": [0.146, -4.84447, -3.39131],
							"rotation": [45, 0, 0],
							"uv": {
								"north": {"uv": [30, 30], "uv_size": [0.5, 0.5]},
								"east": {"uv": [0, 31], "uv_size": [0.5, 0.5]},
								"south": {"uv": [31, 0], "uv_size": [0.5, 0.5]},
								"west": {"uv": [1, 31], "uv_size": [0.5, 0.5]},
								"up": {"uv": [31, 1], "uv_size": [0.5, 0.5]},
								"down": {"uv": [2, 31.5], "uv_size": [0.5, -0.5]}
							}
						},
						{
							"origin": [-0.03125, -4.52276, -1.50625],
							"size": [0.0625, 0.21875, 1.40625],
							"pivot": [0.146, -4.45, -0.71875],
							"rotation": [-45, 0, 0],
							"uv": {
								"north": {"uv": [31, 2], "uv_size": [0.5, 0.5]},
								"east": {"uv": [25, 17], "uv_size": [1.5, 0.5]},
								"south": {"uv": [3, 31], "uv_size": [0.5, 0.5]},
								"west": {"uv": [25, 18], "uv_size": [1.5, 0.5]},
								"up": {"uv": [17, 25], "uv_size": [0.5, 1.5]},
								"down": {"uv": [19, 26.5], "uv_size": [0.5, -1.5]}
							}
						},
						{
							"origin": [-0.03125, -4.41153, -11.38639],
							"size": [0.0625, 0.51875, 3.88125],
							"pivot": [0.146, -4.25, -9.7],
							"rotation": [-6, 0, 0],
							"uv": {
								"north": {"uv": [31, 3], "uv_size": [0.5, 0.5]},
								"east": {"uv": [11, 16], "uv_size": [4, 0.5]},
								"south": {"uv": [4, 31], "uv_size": [0.5, 0.5]},
								"west": {"uv": [16, 11], "uv_size": [4, 0.5]},
								"up": {"uv": [15, 16], "uv_size": [0.5, 4]},
								"down": {"uv": [16, 20], "uv_size": [0.5, -4]}
							}
						},
						{
							"origin": [-0.03125, -4.58653, -7.18639],
							"size": [0.0625, 0.31875, 3.88125],
							"pivot": [0.146, -4.425, -5.5],
							"rotation": [-8.5, 0, 0],
							"uv": {
								"north": {"uv": [31, 4], "uv_size": [0.5, 0.5]},
								"east": {"uv": [17, 2], "uv_size": [4, 0.5]},
								"south": {"uv": [5, 31], "uv_size": [0.5, 0.5]},
								"west": {"uv": [17, 3], "uv_size": [4, 0.5]},
								"up": {"uv": [17, 7], "uv_size": [0.5, 4]},
								"down": {"uv": [8, 21], "uv_size": [0.5, -4]}
							}
						},
						{
							"origin": [-0.03125, -4.28653, -5.88639],
							"size": [0.0625, 0.41875, 2.38125],
							"pivot": [0.146, -4.425, -5.5],
							"rotation": [-8.5, 0, 0],
							"uv": {
								"north": {"uv": [31, 5], "uv_size": [0.5, 0.5]},
								"east": {"uv": [20, 19], "uv_size": [2.5, 0.5]},
								"south": {"uv": [6, 31], "uv_size": [0.5, 0.5]},
								"west": {"uv": [21, 0], "uv_size": [2.5, 0.5]},
								"up": {"uv": [8, 21], "uv_size": [0.5, 2.5]},
								"down": {"uv": [9, 23.5], "uv_size": [0.5, -2.5]}
							}
						},
						{
							"origin": [-0.03125, -3.19053, -13.72178],
							"size": [0.0625, 0.21875, 2.68125],
							"pivot": [0.146, -3.029, -13.23539],
							"rotation": [-29, 0, 0],
							"uv": {
								"north": {"uv": [31, 6], "uv_size": [0.5, 0.5]},
								"east": {"uv": [21, 5], "uv_size": [2.5, 0.5]},
								"south": {"uv": [7, 31], "uv_size": [0.5, 0.5]},
								"west": {"uv": [11, 21], "uv_size": [2.5, 0.5]},
								"up": {"uv": [14, 21], "uv_size": [0.5, 2.5]},
								"down": {"uv": [18, 23.5], "uv_size": [0.5, -2.5]}
							}
						},
						{
							"origin": [-0.03125, -2.99053, -13.37178],
							"size": [0.0625, 0.21875, 2.73125],
							"pivot": [0.146, -3.029, -13.23539],
							"rotation": [-29, 0, 0],
							"uv": {
								"north": {"uv": [31, 7], "uv_size": [0.5, 0.5]},
								"east": {"uv": [21, 12], "uv_size": [2.5, 0.5]},
								"south": {"uv": [8, 31], "uv_size": [0.5, 0.5]},
								"west": {"uv": [21, 16], "uv_size": [2.5, 0.5]},
								"up": {"uv": [19, 21], "uv_size": [0.5, 2.5]},
								"down": {"uv": [20, 23.5], "uv_size": [0.5, -2.5]}
							}
						},
						{
							"origin": [-0.03125, -2.81553, -12.62178],
							"size": [0.0625, 0.34375, 2.35625],
							"pivot": [0.146, -3.029, -13.23539],
							"rotation": [-29, 0, 0],
							"uv": {
								"north": {"uv": [31, 8], "uv_size": [0.5, 0.5]},
								"east": {"uv": [21, 17], "uv_size": [2.5, 0.5]},
								"south": {"uv": [9, 31], "uv_size": [0.5, 0.5]},
								"west": {"uv": [21, 20], "uv_size": [2.5, 0.5]},
								"up": {"uv": [21, 21], "uv_size": [0.5, 2.5]},
								"down": {"uv": [0, 24.5], "uv_size": [0.5, -2.5]}
							}
						},
						{
							"origin": [-0.03125, -4.08591, -10.3365],
							"size": [0.0625, 0.41875, 0.63125],
							"pivot": [0.146, -0.51315, -8.174],
							"rotation": [40, 0, 0],
							"uv": {
								"north": {"uv": [31, 9], "uv_size": [0.5, 0.5]},
								"east": {"uv": [10, 31], "uv_size": [0.5, 0.5]},
								"south": {"uv": [31, 10], "uv_size": [0.5, 0.5]},
								"west": {"uv": [11, 31], "uv_size": [0.5, 0.5]},
								"up": {"uv": [31, 11], "uv_size": [0.5, 0.5]},
								"down": {"uv": [12, 31.5], "uv_size": [0.5, -0.5]}
							}
						}
					]
				},
				{
					"name": "bone5",
					"parent": "cid",
					"pivot": [0.146, 0, -2],
					"cubes": [
						{
							"origin": [-0.15625, -3.27276, -3.4625],
							"size": [0.3125, 0.21875, 3.60625],
							"uv": {
								"north": {"uv": [31, 12], "uv_size": [0.5, 0.5]},
								"east": {"uv": [18, 9], "uv_size": [3.5, 0.5]},
								"south": {"uv": [13, 31], "uv_size": [0.5, 0.5]},
								"west": {"uv": [18, 10], "uv_size": [3.5, 0.5]},
								"up": {"uv": [1, 18], "uv_size": [0.5, 3.5]},
								"down": {"uv": [6, 21.5], "uv_size": [0.5, -3.5]}
							}
						},
						{
							"origin": [-0.15625, -3.42276, -5.2625],
							"size": [0.3125, 0.21875, 1.88125],
							"uv": {
								"north": {"uv": [31, 13], "uv_size": [0.5, 0.5]},
								"east": {"uv": [22, 4], "uv_size": [2, 0.5]},
								"south": {"uv": [14, 31], "uv_size": [0.5, 0.5]},
								"west": {"uv": [12, 22], "uv_size": [2, 0.5]},
								"up": {"uv": [22, 13], "uv_size": [0.5, 2]},
								"down": {"uv": [17, 24], "uv_size": [0.5, -2]}
							}
						},
						{
							"origin": [-0.15625, -3.12276, -5.4375],
							"size": [0.3125, 0.11875, 2.25625],
							"uv": {
								"north": {"uv": [31, 14], "uv_size": [0.5, 0.5]},
								"east": {"uv": [22, 2], "uv_size": [2.5, 0.5]},
								"south": {"uv": [15, 31], "uv_size": [0.5, 0.5]},
								"west": {"uv": [22, 3], "uv_size": [2.5, 0.5]},
								"up": {"uv": [1, 22], "uv_size": [0.5, 2.5]},
								"down": {"uv": [6, 24.5], "uv_size": [0.5, -2.5]}
							}
						},
						{
							"origin": [-0.15625, -2.67276, -3.0625],
							"size": [0.3125, 0.21875, 3.20625],
							"uv": {
								"north": {"uv": [31, 15], "uv_size": [0.5, 0.5]},
								"east": {"uv": [20, 1], "uv_size": [3, 0.5]},
								"south": {"uv": [16, 31], "uv_size": [0.5, 0.5]},
								"west": {"uv": [20, 6], "uv_size": [3, 0.5]},
								"up": {"uv": [4, 20], "uv_size": [0.5, 3]},
								"down": {"uv": [5, 23], "uv_size": [0.5, -3]}
							}
						},
						{
							"origin": [-0.05625, -2.67276, -3.0875],
							"size": [0.1125, 0.24375, 3.25625],
							"uv": {
								"north": {"uv": [31, 16], "uv_size": [0.5, 0.5]},
								"east": {"uv": [18, 13], "uv_size": [3.5, 0.5]},
								"south": {"uv": [17, 31], "uv_size": [0.5, 0.5]},
								"west": {"uv": [18, 14], "uv_size": [3.5, 0.5]},
								"up": {"uv": [7, 18], "uv_size": [0.5, 3.5]},
								"down": {"uv": [17, 21.5], "uv_size": [0.5, -3.5]}
							}
						},
						{
							"origin": [-0.10625, -3.67276, -3.0625],
							"size": [0.2125, 1.11875, 3.20625],
							"uv": {
								"north": {"uv": [7, 26], "uv_size": [0.5, 1]},
								"east": {"uv": [10, 10], "uv_size": [3, 1]},
								"south": {"uv": [26, 7], "uv_size": [0.5, 1]},
								"west": {"uv": [11, 0], "uv_size": [3, 1]},
								"up": {"uv": [10, 20], "uv_size": [0.5, 3]},
								"down": {"uv": [15, 23], "uv_size": [0.5, -3]}
							}
						},
						{
							"origin": [-0.10625, -3.67276, -3.4625],
							"size": [0.2125, 0.51875, 0.50625],
							"uv": {
								"north": {"uv": [31, 17], "uv_size": [0.5, 0.5]},
								"east": {"uv": [18, 31], "uv_size": [0.5, 0.5]},
								"south": {"uv": [31, 18], "uv_size": [0.5, 0.5]},
								"west": {"uv": [19, 31], "uv_size": [0.5, 0.5]},
								"up": {"uv": [31, 19], "uv_size": [0.5, 0.5]},
								"down": {"uv": [20, 31.5], "uv_size": [0.5, -0.5]}
							}
						},
						{
							"origin": [-0.10625, -3.27276, -5.3625],
							"size": [0.2125, 0.16875, 2.18125],
							"uv": {
								"north": {"uv": [31, 20], "uv_size": [0.5, 0.5]},
								"east": {"uv": [22, 15], "uv_size": [2, 0.5]},
								"south": {"uv": [21, 31], "uv_size": [0.5, 0.5]},
								"west": {"uv": [22, 18], "uv_size": [2, 0.5]},
								"up": {"uv": [22, 21], "uv_size": [0.5, 2]},
								"down": {"uv": [2, 25], "uv_size": [0.5, -2]}
							}
						},
						{
							"origin": [-0.15625, -3.27276, -6.75067],
							"size": [0.3125, 0.23768, 0.79442],
							"pivot": [0.146, 0.3, -4.6],
							"rotation": [45, 0, 0],
							"uv": {
								"north": {"uv": [31, 21], "uv_size": [0.5, 0.5]},
								"east": {"uv": [8, 26], "uv_size": [1, 0.5]},
								"south": {"uv": [22, 31], "uv_size": [0.5, 0.5]},
								"west": {"uv": [26, 8], "uv_size": [1, 0.5]},
								"up": {"uv": [9, 26], "uv_size": [0.5, 1]},
								"down": {"uv": [26, 10], "uv_size": [0.5, -1]}
							}
						},
						{
							"origin": [-0.15625, -3.27276, -5.4625],
							"size": [0.3125, 0.21875, 0.80625],
							"pivot": [0.146, 0.3, -3.3],
							"rotation": [45, 0, 0],
							"uv": {
								"north": {"uv": [31, 22], "uv_size": [0.5, 0.5]},
								"east": {"uv": [11, 26], "uv_size": [1, 0.5]},
								"south": {"uv": [23, 31], "uv_size": [0.5, 0.5]},
								"west": {"uv": [26, 11], "uv_size": [1, 0.5]},
								"up": {"uv": [12, 26], "uv_size": [0.5, 1]},
								"down": {"uv": [26, 13], "uv_size": [0.5, -1]}
							}
						},
						{
							"origin": [-0.15625, -3.37276, -5.9625],
							"size": [0.3125, 0.21875, 0.60625],
							"pivot": [0.146, 0.2, -4],
							"rotation": [62.5, 0, 0],
							"uv": {
								"north": {"uv": [31, 23], "uv_size": [0.5, 0.5]},
								"east": {"uv": [24, 31], "uv_size": [0.5, 0.5]},
								"south": {"uv": [31, 24], "uv_size": [0.5, 0.5]},
								"west": {"uv": [25, 31], "uv_size": [0.5, 0.5]},
								"up": {"uv": [31, 25], "uv_size": [0.5, 0.5]},
								"down": {"uv": [26, 31.5], "uv_size": [0.5, -0.5]}
							}
						},
						{
							"origin": [-0.15625, -3.37276, -6.3625],
							"size": [0.3125, 0.21875, 0.60625],
							"pivot": [0.146, 0.2, -4.4],
							"rotation": [62.5, 0, 0],
							"uv": {
								"north": {"uv": [31, 26], "uv_size": [0.5, 0.5]},
								"east": {"uv": [27, 31], "uv_size": [0.5, 0.5]},
								"south": {"uv": [31, 27], "uv_size": [0.5, 0.5]},
								"west": {"uv": [28, 31], "uv_size": [0.5, 0.5]},
								"up": {"uv": [31, 28], "uv_size": [0.5, 0.5]},
								"down": {"uv": [29, 31.5], "uv_size": [0.5, -0.5]}
							}
						},
						{
							"origin": [-0.15625, -3.37276, -5.3625],
							"size": [0.3125, 0.21875, 0.60625],
							"pivot": [0.146, 0.2, -3.4],
							"rotation": [62.5, 0, 0],
							"uv": {
								"north": {"uv": [31, 29], "uv_size": [0.5, 0.5]},
								"east": {"uv": [30, 31], "uv_size": [0.5, 0.5]},
								"south": {"uv": [31, 30], "uv_size": [0.5, 0.5]},
								"west": {"uv": [31, 31], "uv_size": [0.5, 0.5]},
								"up": {"uv": [0, 32], "uv_size": [0.5, 0.5]},
								"down": {"uv": [32, 0.5], "uv_size": [0.5, -0.5]}
							}
						},
						{
							"origin": [-0.15625, -3.37276, -4.3625],
							"size": [0.3125, 0.21875, 0.60625],
							"pivot": [0.146, 0.2, -2.4],
							"rotation": [62.5, 0, 0],
							"uv": {
								"north": {"uv": [1, 32], "uv_size": [0.5, 0.5]},
								"east": {"uv": [32, 1], "uv_size": [0.5, 0.5]},
								"south": {"uv": [2, 32], "uv_size": [0.5, 0.5]},
								"west": {"uv": [32, 2], "uv_size": [0.5, 0.5]},
								"up": {"uv": [3, 32], "uv_size": [0.5, 0.5]},
								"down": {"uv": [32, 3.5], "uv_size": [0.5, -0.5]}
							}
						},
						{
							"origin": [-0.15625, -3.37276, -4.1625],
							"size": [0.3125, 0.21875, 0.60625],
							"pivot": [0.146, 0.2, -2.2],
							"rotation": [62.5, 0, 0],
							"uv": {
								"north": {"uv": [4, 32], "uv_size": [0.5, 0.5]},
								"east": {"uv": [32, 4], "uv_size": [0.5, 0.5]},
								"south": {"uv": [5, 32], "uv_size": [0.5, 0.5]},
								"west": {"uv": [32, 5], "uv_size": [0.5, 0.5]},
								"up": {"uv": [6, 32], "uv_size": [0.5, 0.5]},
								"down": {"uv": [32, 6.5], "uv_size": [0.5, -0.5]}
							}
						},
						{
							"origin": [-0.15625, -3.37276, -5.1625],
							"size": [0.3125, 0.21875, 0.60625],
							"pivot": [0.146, 0.2, -3.2],
							"rotation": [62.5, 0, 0],
							"uv": {
								"north": {"uv": [7, 32], "uv_size": [0.5, 0.5]},
								"east": {"uv": [32, 7], "uv_size": [0.5, 0.5]},
								"south": {"uv": [8, 32], "uv_size": [0.5, 0.5]},
								"west": {"uv": [32, 8], "uv_size": [0.5, 0.5]},
								"up": {"uv": [9, 32], "uv_size": [0.5, 0.5]},
								"down": {"uv": [32, 9.5], "uv_size": [0.5, -0.5]}
							}
						},
						{
							"origin": [-0.15625, -3.37276, -4.9625],
							"size": [0.3125, 0.21875, 0.60625],
							"pivot": [0.146, 0.2, -3],
							"rotation": [62.5, 0, 0],
							"uv": {
								"north": {"uv": [10, 32], "uv_size": [0.5, 0.5]},
								"east": {"uv": [32, 10], "uv_size": [0.5, 0.5]},
								"south": {"uv": [11, 32], "uv_size": [0.5, 0.5]},
								"west": {"uv": [32, 11], "uv_size": [0.5, 0.5]},
								"up": {"uv": [12, 32], "uv_size": [0.5, 0.5]},
								"down": {"uv": [32, 12.5], "uv_size": [0.5, -0.5]}
							}
						},
						{
							"origin": [-0.15625, -3.37276, -7.3625],
							"size": [0.3125, 0.21875, 0.60625],
							"pivot": [0.146, 0.2, -5.4],
							"rotation": [62.5, 0, 0],
							"uv": {
								"north": {"uv": [13, 32], "uv_size": [0.5, 0.5]},
								"east": {"uv": [32, 13], "uv_size": [0.5, 0.5]},
								"south": {"uv": [14, 32], "uv_size": [0.5, 0.5]},
								"west": {"uv": [32, 14], "uv_size": [0.5, 0.5]},
								"up": {"uv": [15, 32], "uv_size": [0.5, 0.5]},
								"down": {"uv": [32, 15.5], "uv_size": [0.5, -0.5]}
							}
						},
						{
							"origin": [-0.15625, -3.37276, -7.1625],
							"size": [0.3125, 0.21875, 0.60625],
							"pivot": [0.146, 0.2, -5.2],
							"rotation": [62.5, 0, 0],
							"uv": {
								"north": {"uv": [16, 32], "uv_size": [0.5, 0.5]},
								"east": {"uv": [32, 16], "uv_size": [0.5, 0.5]},
								"south": {"uv": [17, 32], "uv_size": [0.5, 0.5]},
								"west": {"uv": [32, 17], "uv_size": [0.5, 0.5]},
								"up": {"uv": [18, 32], "uv_size": [0.5, 0.5]},
								"down": {"uv": [32, 18.5], "uv_size": [0.5, -0.5]}
							}
						},
						{
							"origin": [-0.15625, -3.37276, -6.1625],
							"size": [0.3125, 0.21875, 0.60625],
							"pivot": [0.146, 0.2, -4.2],
							"rotation": [62.5, 0, 0],
							"uv": {
								"north": {"uv": [19, 32], "uv_size": [0.5, 0.5]},
								"east": {"uv": [32, 19], "uv_size": [0.5, 0.5]},
								"south": {"uv": [20, 32], "uv_size": [0.5, 0.5]},
								"west": {"uv": [32, 20], "uv_size": [0.5, 0.5]},
								"up": {"uv": [21, 32], "uv_size": [0.5, 0.5]},
								"down": {"uv": [32, 21.5], "uv_size": [0.5, -0.5]}
							}
						},
						{
							"origin": [-0.15625, -3.37276, -6.9625],
							"size": [0.3125, 0.21875, 0.60625],
							"pivot": [0.146, 0.2, -5],
							"rotation": [62.5, 0, 0],
							"uv": {
								"north": {"uv": [22, 32], "uv_size": [0.5, 0.5]},
								"east": {"uv": [32, 22], "uv_size": [0.5, 0.5]},
								"south": {"uv": [23, 32], "uv_size": [0.5, 0.5]},
								"west": {"uv": [32, 23], "uv_size": [0.5, 0.5]},
								"up": {"uv": [24, 32], "uv_size": [0.5, 0.5]},
								"down": {"uv": [32, 24.5], "uv_size": [0.5, -0.5]}
							}
						},
						{
							"origin": [-0.15625, -3.27276, 1.25625],
							"size": [0.3125, 0.21875, 0.80625],
							"pivot": [0.146, 0.3, -0.1],
							"rotation": [-45, 0, 0],
							"uv": {
								"north": {"uv": [25, 32], "uv_size": [0.5, 0.5]},
								"east": {"uv": [13, 26], "uv_size": [1, 0.5]},
								"south": {"uv": [32, 25], "uv_size": [0.5, 0.5]},
								"west": {"uv": [14, 26], "uv_size": [1, 0.5]},
								"up": {"uv": [26, 14], "uv_size": [0.5, 1]},
								"down": {"uv": [15, 27], "uv_size": [0.5, -1]}
							}
						},
						{
							"origin": [-0.15625, -3.27276, -0.14375],
							"size": [0.3125, 0.21875, 0.80625],
							"pivot": [0.146, 0.3, -1.5],
							"rotation": [-45, 0, 0],
							"uv": {
								"north": {"uv": [26, 32], "uv_size": [0.5, 0.5]},
								"east": {"uv": [26, 15], "uv_size": [1, 0.5]},
								"south": {"uv": [32, 26], "uv_size": [0.5, 0.5]},
								"west": {"uv": [26, 16], "uv_size": [1, 0.5]},
								"up": {"uv": [18, 26], "uv_size": [0.5, 1]},
								"down": {"uv": [26, 21], "uv_size": [0.5, -1]}
							}
						},
						{
							"origin": [-0.15625, -2.94008, -2.52264],
							"size": [0.3125, 0.17236, 0.41984],
							"pivot": [0.146, 0.63268, -4.2653],
							"rotation": [-45, 0, 0],
							"uv": {
								"north": {"uv": [27, 32], "uv_size": [0.5, 0.5]},
								"east": {"uv": [32, 27], "uv_size": [0.5, 0.5]},
								"south": {"uv": [28, 32], "uv_size": [0.5, 0.5]},
								"west": {"uv": [32, 28], "uv_size": [0.5, 0.5]},
								"up": {"uv": [29, 32], "uv_size": [0.5, 0.5]},
								"down": {"uv": [32, 29.5], "uv_size": [0.5, -0.5]}
							}
						},
						{
							"origin": [-0.15625, -3.27276, -4.1875],
							"size": [0.3125, 0.21875, 1.23125],
							"pivot": [0.146, 0.3, -1.6],
							"rotation": [45, 0, 0],
							"uv": {
								"north": {"uv": [30, 32], "uv_size": [0.5, 0.5]},
								"east": {"uv": [21, 26], "uv_size": [1, 0.5]},
								"south": {"uv": [32, 30], "uv_size": [0.5, 0.5]},
								"west": {"uv": [26, 22], "uv_size": [1, 0.5]},
								"up": {"uv": [23, 26], "uv_size": [0.5, 1]},
								"down": {"uv": [26, 24], "uv_size": [0.5, -1]}
							}
						},
						{
							"origin": [-0.15625, -3.27276, -4.1875],
							"size": [0.3125, 0.36875, 0.20625],
							"pivot": [0.146, 0.3, -1.6],
							"rotation": [45, 0, 0],
							"uv": {
								"north": {"uv": [31, 32], "uv_size": [0.5, 0.5]},
								"east": {"uv": [32, 31], "uv_size": [0.5, 0.5]},
								"south": {"uv": [32, 32], "uv_size": [0.5, 0.5]},
								"west": {"uv": [0, 33], "uv_size": [0.5, 0.5]},
								"up": {"uv": [33, 0], "uv_size": [0.5, 0.5]},
								"down": {"uv": [1, 33.5], "uv_size": [0.5, -0.5]}
							}
						},
						{
							"origin": [-0.18125, -3.87276, -4.2125],
							"size": [0.3625, 0.59375, 1.38125],
							"pivot": [0.146, 0.3, -1.6],
							"rotation": [45, 0, 0],
							"uv": {
								"north": {"uv": [33, 1], "uv_size": [0.5, 0.5]},
								"east": {"uv": [25, 19], "uv_size": [1.5, 0.5]},
								"south": {"uv": [2, 33], "uv_size": [0.5, 0.5]},
								"west": {"uv": [25, 21], "uv_size": [1.5, 0.5]},
								"up": {"uv": [20, 25], "uv_size": [0.5, 1.5]},
								"down": {"uv": [22, 26.5], "uv_size": [0.5, -1.5]}
							}
						},
						{
							"origin": [-0.15625, -3.79776, -3.7625],
							"size": [0.3125, 0.21875, 3.33125],
							"uv": {
								"north": {"uv": [33, 2], "uv_size": [0.5, 0.5]},
								"east": {"uv": [18, 15], "uv_size": [3.5, 0.5]},
								"south": {"uv": [3, 33], "uv_size": [0.5, 0.5]},
								"west": {"uv": [18, 18], "uv_size": [3.5, 0.5]},
								"up": {"uv": [2, 19], "uv_size": [0.5, 3.5]},
								"down": {"uv": [3, 22.5], "uv_size": [0.5, -3.5]}
							}
						}
					]
				},
				{
					"name": "bone4",
					"parent": "cid",
					"pivot": [0, -3.39062, 1.23438],
					"cubes": [
						{
							"origin": [-0.31969, -3.07054, 1.00261],
							"size": [0.63938, 0.12688, 0.30634],
							"pivot": [0.02518, -3.10187, 0.0701],
							"rotation": [-22.5, 0, 0],
							"uv": {
								"north": {"uv": [33, 3], "uv_size": [0.5, 0.5]},
								"east": {"uv": [4, 33], "uv_size": [0.5, 0.5]},
								"south": {"uv": [33, 4], "uv_size": [0.5, 0.5]},
								"west": {"uv": [5, 33], "uv_size": [0.5, 0.5]},
								"up": {"uv": [33, 5], "uv_size": [0.5, 0.5]},
								"down": {"uv": [6, 33.5], "uv_size": [0.5, -0.5]}
							}
						},
						{
							"origin": [-0.31969, -3.16026, 1.09233],
							"size": [0.63938, 0.30634, 0.12688],
							"pivot": [0.02518, -3.10187, 0.0701],
							"rotation": [-22.5, 0, 0],
							"uv": {
								"north": {"uv": [33, 6], "uv_size": [0.5, 0.5]},
								"east": {"uv": [7, 33], "uv_size": [0.5, 0.5]},
								"south": {"uv": [33, 7], "uv_size": [0.5, 0.5]},
								"west": {"uv": [8, 33], "uv_size": [0.5, 0.5]},
								"up": {"uv": [33, 8], "uv_size": [0.5, 0.5]},
								"down": {"uv": [9, 33.5], "uv_size": [0.5, -0.5]}
							}
						},
						{
							"origin": [-0.31969, -3.9557, 0.84137],
							"size": [0.63938, 0.30634, 0.12688],
							"pivot": [0.02518, -3.10187, 0.0701],
							"rotation": [22.5, 0, 0],
							"uv": {
								"north": {"uv": [33, 9], "uv_size": [0.5, 0.5]},
								"east": {"uv": [10, 33], "uv_size": [0.5, 0.5]},
								"south": {"uv": [33, 10], "uv_size": [0.5, 0.5]},
								"west": {"uv": [11, 33], "uv_size": [0.5, 0.5]},
								"up": {"uv": [33, 11], "uv_size": [0.5, 0.5]},
								"down": {"uv": [12, 33.5], "uv_size": [0.5, -0.5]}
							}
						},
						{
							"origin": [-0.31969, -3.86598, 0.75165],
							"size": [0.63938, 0.12688, 0.30634],
							"pivot": [0.02518, -3.10187, 0.0701],
							"rotation": [22.5, 0, 0],
							"uv": {
								"north": {"uv": [33, 12], "uv_size": [0.5, 0.5]},
								"east": {"uv": [13, 33], "uv_size": [0.5, 0.5]},
								"south": {"uv": [33, 13], "uv_size": [0.5, 0.5]},
								"west": {"uv": [14, 33], "uv_size": [0.5, 0.5]},
								"up": {"uv": [33, 14], "uv_size": [0.5, 0.5]},
								"down": {"uv": [15, 33.5], "uv_size": [0.5, -0.5]}
							}
						}
					]
				},
				{
					"name": "bone11",
					"parent": "cid",
					"pivot": [0, -1.53125, 0.98438],
					"cubes": [
						{
							"origin": [-0.20478, -2.05793, 0.04003],
							"size": [0.42399, 0.1706, 0.25812],
							"uv": {
								"north": {"uv": [33, 15], "uv_size": [0.5, 0.5]},
								"east": {"uv": [16, 33], "uv_size": [0.5, 0.5]},
								"south": {"uv": [33, 16], "uv_size": [0.5, 0.5]},
								"west": {"uv": [17, 33], "uv_size": [0.5, 0.5]},
								"up": {"uv": [33, 17], "uv_size": [0.5, 0.5]},
								"down": {"uv": [18, 33.5], "uv_size": [0.5, -0.5]}
							}
						},
						{
							"origin": [-0.20478, -2.05793, 0.04003],
							"size": [0.42399, 0.1706, 0.25812],
							"pivot": [0.00721, -1.54614, 2.74136],
							"rotation": [0, 0, 45],
							"uv": {
								"north": {"uv": [33, 18], "uv_size": [0.5, 0.5]},
								"east": {"uv": [19, 33], "uv_size": [0.5, 0.5]},
								"south": {"uv": [33, 19], "uv_size": [0.5, 0.5]},
								"west": {"uv": [20, 33], "uv_size": [0.5, 0.5]},
								"up": {"uv": [33, 20], "uv_size": [0.5, 0.5]},
								"down": {"uv": [21, 33.5], "uv_size": [0.5, -0.5]}
							}
						},
						{
							"origin": [-0.50458, -1.75813, 0.04003],
							"size": [0.1706, 0.42399, 0.25812],
							"uv": {
								"north": {"uv": [33, 21], "uv_size": [0.5, 0.5]},
								"east": {"uv": [22, 33], "uv_size": [0.5, 0.5]},
								"south": {"uv": [33, 22], "uv_size": [0.5, 0.5]},
								"west": {"uv": [23, 33], "uv_size": [0.5, 0.5]},
								"up": {"uv": [33, 23], "uv_size": [0.5, 0.5]},
								"down": {"uv": [24, 33.5], "uv_size": [0.5, -0.5]}
							}
						},
						{
							"origin": [-0.50458, -1.75813, 0.04003],
							"size": [0.1706, 0.42399, 0.25812],
							"pivot": [0.00721, -1.54614, 2.74136],
							"rotation": [0, 0, 45],
							"uv": {
								"north": {"uv": [33, 24], "uv_size": [0.5, 0.5]},
								"east": {"uv": [25, 33], "uv_size": [0.5, 0.5]},
								"south": {"uv": [33, 25], "uv_size": [0.5, 0.5]},
								"west": {"uv": [26, 33], "uv_size": [0.5, 0.5]},
								"up": {"uv": [33, 26], "uv_size": [0.5, 0.5]},
								"down": {"uv": [27, 33.5], "uv_size": [0.5, -0.5]}
							}
						},
						{
							"origin": [-0.20478, -1.20494, 0.04003],
							"size": [0.42399, 0.1706, 0.25812],
							"uv": {
								"north": {"uv": [33, 27], "uv_size": [0.5, 0.5]},
								"east": {"uv": [28, 33], "uv_size": [0.5, 0.5]},
								"south": {"uv": [33, 28], "uv_size": [0.5, 0.5]},
								"west": {"uv": [29, 33], "uv_size": [0.5, 0.5]},
								"up": {"uv": [33, 29], "uv_size": [0.5, 0.5]},
								"down": {"uv": [30, 33.5], "uv_size": [0.5, -0.5]}
							}
						},
						{
							"origin": [-0.20478, -1.20494, 0.04003],
							"size": [0.42399, 0.1706, 0.25812],
							"pivot": [0.00721, -1.54614, 2.74136],
							"rotation": [0, 0, 45],
							"uv": {
								"north": {"uv": [33, 30], "uv_size": [0.5, 0.5]},
								"east": {"uv": [31, 33], "uv_size": [0.5, 0.5]},
								"south": {"uv": [33, 31], "uv_size": [0.5, 0.5]},
								"west": {"uv": [32, 33], "uv_size": [0.5, 0.5]},
								"up": {"uv": [33, 32], "uv_size": [0.5, 0.5]},
								"down": {"uv": [33, 33.5], "uv_size": [0.5, -0.5]}
							}
						},
						{
							"origin": [0.34841, -1.75813, 0.04003],
							"size": [0.1706, 0.42399, 0.25812],
							"uv": {
								"north": {"uv": [0, 34], "uv_size": [0.5, 0.5]},
								"east": {"uv": [34, 0], "uv_size": [0.5, 0.5]},
								"south": {"uv": [1, 34], "uv_size": [0.5, 0.5]},
								"west": {"uv": [34, 1], "uv_size": [0.5, 0.5]},
								"up": {"uv": [2, 34], "uv_size": [0.5, 0.5]},
								"down": {"uv": [34, 2.5], "uv_size": [0.5, -0.5]}
							}
						},
						{
							"origin": [0.34841, -1.75813, 0.04003],
							"size": [0.1706, 0.42399, 0.25812],
							"pivot": [0.00721, -1.54614, 2.74136],
							"rotation": [0, 0, 45],
							"uv": {
								"north": {"uv": [3, 34], "uv_size": [0.5, 0.5]},
								"east": {"uv": [34, 3], "uv_size": [0.5, 0.5]},
								"south": {"uv": [4, 34], "uv_size": [0.5, 0.5]},
								"west": {"uv": [34, 4], "uv_size": [0.5, 0.5]},
								"up": {"uv": [5, 34], "uv_size": [0.5, 0.5]},
								"down": {"uv": [34, 5.5], "uv_size": [0.5, -0.5]}
							}
						}
					]
				},
				{
					"name": "bone12",
					"parent": "cid",
					"pivot": [0, -2, 0.98438],
					"cubes": [
						{
							"origin": [-0.39346, -2.84092, 5.10938],
							"size": [0.78691, 0.09092, 1],
							"uv": {
								"north": {"uv": [24, 26], "uv_size": [1, 0.5]},
								"east": {"uv": [26, 24], "uv_size": [1, 0.5]},
								"south": {"uv": [25, 26], "uv_size": [1, 0.5]},
								"west": {"uv": [26, 25], "uv_size": [1, 0.5]},
								"up": {"uv": [23, 1], "uv_size": [1, 1]},
								"down": {"uv": [3, 24], "uv_size": [1, -1]}
							}
						},
						{
							"origin": [-2.06608, -3.80643, 5.10938],
							"size": [0.12858, 0.13456, 1],
							"pivot": [0, -5.1875, 6.07813],
							"rotation": [0, 0, 45],
							"uv": {
								"north": {"uv": [6, 34], "uv_size": [0.5, 0.5]},
								"east": {"uv": [26, 26], "uv_size": [1, 0.5]},
								"south": {"uv": [34, 6], "uv_size": [0.5, 0.5]},
								"west": {"uv": [0, 27], "uv_size": [1, 0.5]},
								"up": {"uv": [27, 0], "uv_size": [0.5, 1]},
								"down": {"uv": [1, 28], "uv_size": [0.5, -1]}
							}
						},
						{
							"origin": [-0.6064, -2.7686, 5.10938],
							"size": [1.2128, 0.0811, 0.99634],
							"uv": {
								"north": {"uv": [27, 1], "uv_size": [1, 0.5]},
								"east": {"uv": [2, 27], "uv_size": [1, 0.5]},
								"south": {"uv": [27, 2], "uv_size": [1, 0.5]},
								"west": {"uv": [3, 27], "uv_size": [1, 0.5]},
								"up": {"uv": [4, 23], "uv_size": [1, 1]},
								"down": {"uv": [5, 24], "uv_size": [1, -1]}
							}
						},
						{
							"origin": [-0.48437, -2.75, 5.10938],
							"size": [0.96875, 0.23438, 1],
							"uv": {
								"north": {"uv": [27, 3], "uv_size": [1, 0.5]},
								"east": {"uv": [4, 27], "uv_size": [1, 0.5]},
								"south": {"uv": [27, 4], "uv_size": [1, 0.5]},
								"west": {"uv": [5, 27], "uv_size": [1, 0.5]},
								"up": {"uv": [23, 6], "uv_size": [1, 1]},
								"down": {"uv": [23, 8], "uv_size": [1, -1]}
							}
						},
						{
							"origin": [0.50937, -1.93105, 5.10938],
							"size": [0.125, 0.11469, 0.99634],
							"pivot": [0.96249, -3.69668, 6.48438],
							"rotation": [0, 0, -45],
							"uv": {
								"north": {"uv": [7, 34], "uv_size": [0.5, 0.5]},
								"east": {"uv": [27, 5], "uv_size": [1, 0.5]},
								"south": {"uv": [34, 7], "uv_size": [0.5, 0.5]},
								"west": {"uv": [6, 27], "uv_size": [1, 0.5]},
								"up": {"uv": [27, 6], "uv_size": [0.5, 1]},
								"down": {"uv": [7, 28], "uv_size": [0.5, -1]}
							}
						},
						{
							"origin": [-0.6875, -2.6875, 5.10938],
							"size": [0.34375, 0.13032, 0.99634],
							"uv": {
								"north": {"uv": [8, 34], "uv_size": [0.5, 0.5]},
								"east": {"uv": [27, 7], "uv_size": [1, 0.5]},
								"south": {"uv": [34, 8], "uv_size": [0.5, 0.5]},
								"west": {"uv": [8, 27], "uv_size": [1, 0.5]},
								"up": {"uv": [27, 8], "uv_size": [0.5, 1]},
								"down": {"uv": [9, 28], "uv_size": [0.5, -1]}
							}
						},
						{
							"origin": [-0.6875, -2.5625, 5.10938],
							"size": [0.34375, 0.3125, 1],
							"uv": {
								"north": {"uv": [9, 34], "uv_size": [0.5, 0.5]},
								"east": {"uv": [27, 9], "uv_size": [1, 0.5]},
								"south": {"uv": [34, 9], "uv_size": [0.5, 0.5]},
								"west": {"uv": [10, 27], "uv_size": [1, 0.5]},
								"up": {"uv": [27, 10], "uv_size": [0.5, 1]},
								"down": {"uv": [11, 28], "uv_size": [0.5, -1]}
							}
						},
						{
							"origin": [-0.63437, -1.93105, 5.10938],
							"size": [0.125, 0.11469, 0.99634],
							"pivot": [-0.96249, -3.69668, 6.48438],
							"rotation": [0, 0, 45],
							"uv": {
								"north": {"uv": [10, 34], "uv_size": [0.5, 0.5]},
								"east": {"uv": [27, 11], "uv_size": [1, 0.5]},
								"south": {"uv": [34, 10], "uv_size": [0.5, 0.5]},
								"west": {"uv": [12, 27], "uv_size": [1, 0.5]},
								"up": {"uv": [27, 12], "uv_size": [0.5, 1]},
								"down": {"uv": [13, 28], "uv_size": [0.5, -1]}
							}
						},
						{
							"origin": [0.34375, -2.6875, 5.10938],
							"size": [0.34375, 0.13032, 0.99634],
							"uv": {
								"north": {"uv": [11, 34], "uv_size": [0.5, 0.5]},
								"east": {"uv": [27, 13], "uv_size": [1, 0.5]},
								"south": {"uv": [34, 11], "uv_size": [0.5, 0.5]},
								"west": {"uv": [14, 27], "uv_size": [1, 0.5]},
								"up": {"uv": [27, 14], "uv_size": [0.5, 1]},
								"down": {"uv": [15, 28], "uv_size": [0.5, -1]}
							}
						},
						{
							"origin": [0.34375, -2.5625, 5.10938],
							"size": [0.34375, 0.3125, 1],
							"uv": {
								"north": {"uv": [12, 34], "uv_size": [0.5, 0.5]},
								"east": {"uv": [27, 15], "uv_size": [1, 0.5]},
								"south": {"uv": [34, 12], "uv_size": [0.5, 0.5]},
								"west": {"uv": [16, 27], "uv_size": [1, 0.5]},
								"up": {"uv": [27, 16], "uv_size": [0.5, 1]},
								"down": {"uv": [17, 28], "uv_size": [0.5, -1]}
							}
						}
					]
				},
				{
					"name": "bone_illuminated",
					"parent": "cid",
					"pivot": [0, -2, 0.98438],
					"cubes": [
						{
							"origin": [-0.30469, -3.03125, 0.28125],
							"size": [0.60938, 0.09375, 4.51563],
							"uv": {
								"east": {"uv": [14, 0], "uv_size": [4.5, 0.5]},
								"west": {"uv": [14, 12], "uv_size": [4.5, 0.5]}
							}
						},
						{
							"origin": [-0.30469, -3.14062, 0.28125],
							"size": [0.60938, 0.04688, 4.51563],
							"uv": {
								"east": {"uv": [13, 14], "uv_size": [4.5, 0.5]},
								"west": {"uv": [13, 15], "uv_size": [4.5, 0.5]}
							}
						}
					]
				},
				{
					"name": "bone",
					"parent": "cid",
					"pivot": [0, -3.39062, 4.23438]
				},
				{
					"name": "bone2",
					"parent": "cid",
					"pivot": [0, -3.39062, 4.23438],
					"cubes": [
						{
							"origin": [-0.31969, -3.07054, 4.00261],
							"size": [0.63938, 0.12688, 0.30634],
							"pivot": [0.02518, -3.10187, 3.0701],
							"rotation": [-22.5, 0, 0],
							"uv": {
								"north": {"uv": [25, 34], "uv_size": [0.5, 0.5]},
								"east": {"uv": [34, 25], "uv_size": [0.5, 0.5]},
								"south": {"uv": [26, 34], "uv_size": [0.5, 0.5]},
								"west": {"uv": [34, 26], "uv_size": [0.5, 0.5]},
								"up": {"uv": [27, 34], "uv_size": [0.5, 0.5]},
								"down": {"uv": [34, 27.5], "uv_size": [0.5, -0.5]}
							}
						},
						{
							"origin": [-0.31969, -3.16026, 4.09233],
							"size": [0.63938, 0.30634, 0.12688],
							"pivot": [0.02518, -3.10187, 3.0701],
							"rotation": [-22.5, 0, 0],
							"uv": {
								"north": {"uv": [28, 34], "uv_size": [0.5, 0.5]},
								"east": {"uv": [34, 28], "uv_size": [0.5, 0.5]},
								"south": {"uv": [29, 34], "uv_size": [0.5, 0.5]},
								"west": {"uv": [34, 29], "uv_size": [0.5, 0.5]},
								"up": {"uv": [30, 34], "uv_size": [0.5, 0.5]},
								"down": {"uv": [34, 30.5], "uv_size": [0.5, -0.5]}
							}
						},
						{
							"origin": [-0.31969, -3.9557, 3.84137],
							"size": [0.63938, 0.30634, 0.12688],
							"pivot": [0.02518, -3.10187, 3.0701],
							"rotation": [22.5, 0, 0],
							"uv": {
								"north": {"uv": [31, 34], "uv_size": [0.5, 0.5]},
								"east": {"uv": [34, 31], "uv_size": [0.5, 0.5]},
								"south": {"uv": [32, 34], "uv_size": [0.5, 0.5]},
								"west": {"uv": [34, 32], "uv_size": [0.5, 0.5]},
								"up": {"uv": [33, 34], "uv_size": [0.5, 0.5]},
								"down": {"uv": [34, 33.5], "uv_size": [0.5, -0.5]}
							}
						},
						{
							"origin": [-0.31969, -3.86598, 3.75165],
							"size": [0.63938, 0.12688, 0.30634],
							"pivot": [0.02518, -3.10187, 3.0701],
							"rotation": [22.5, 0, 0],
							"uv": {
								"north": {"uv": [34, 34], "uv_size": [0.5, 0.5]},
								"east": {"uv": [0, 35], "uv_size": [0.5, 0.5]},
								"south": {"uv": [35, 0], "uv_size": [0.5, 0.5]},
								"west": {"uv": [1, 35], "uv_size": [0.5, 0.5]},
								"up": {"uv": [35, 1], "uv_size": [0.5, 0.5]},
								"down": {"uv": [2, 35.5], "uv_size": [0.5, -0.5]}
							}
						}
					]
				}
			]
		}
	]
}